{"kill_data":{"deaths_7d":0,"mob_deaths_7d":0,"mob_kills_total":43,"player_kdr_30d":"0","player_kills_7d":0,"player_deaths_total":0,"deaths_30d":0,"deaths_total":17,"player_kills_total":0,"mob_deaths_30d":0,"player_deaths_30d":0,"mob_kdr_30d":"0","player_kdr_total":"0","weapon_3rd":"-","mob_kdr_7d":"0","player_kdr_7d":"0","player_kills_30d":0,"weapon_2nd":"-","player_deaths_7d":0,"mob_deaths_total":17,"mob_kills_7d":0,"mob_kdr_total":"2.53","weapon_1st":"-","mob_kills_30d":0},"sessions":[{"server_name":"Survival","start":"Aug 18 2021, 13:16","length":"4s","gm_series":[{"data":[["SURVIVAL",4591],["SPECTATOR",0],["CREATIVE",0],["ADVENTURE",0]],"name":"NordicEraI","id":"NordicEraI"}],"player_uuid":"75a39539-384a-4c54-88c6-9e0454a7e90c","most_used_world":"NordicEraI (100%)","first_session":false,"mob_kills":0,"player_url_name":"MossyPickle16","afk_time":"0s","name":"Survival","player_kills":[],"end":"Aug 18 2021, 13:16","player_name":"MossyPickle16","world_series":[{"name":"NordicEraI","y":4591,"color":"#0099C6","drilldown":"NordicEraI"}],"server_url_name":"Survival","server_uuid":"89eae527-4566-404d-a8f5-88200718a4d7","deaths":0},{"server_name":"Survival","start":"Aug 16 2021, 19:56","length":"18m 58s","gm_series":[{"data":[["SURVIVAL",1138406],["SPECTATOR",0],["CREATIVE",0],["ADVENTURE",0]],"name":"NordicEraI","id":"NordicEraI"}],"player_uuid":"75a39539-384a-4c54-88c6-9e0454a7e90c","most_used_world":"NordicEraI (100%)","first_session":false,"mob_kills":0,"player_url_name":"MossyPickle16","afk_time":"0s","name":"Survival","player_kills":[],"end":"Aug 16 2021, 20:15","player_name":"MossyPickle16","world_series":[{"name":"NordicEraI","y":1138406,"color":"#0099C6","drilldown":"NordicEraI"}],"server_url_name":"Survival","server_uuid":"89eae527-4566-404d-a8f5-88200718a4d7","deaths":0},{"server_name":"Survival","start":"Aug 16 2021, 19:32","length":"6m 38s","gm_series":[{"data":[["SURVIVAL",398848],["SPECTATOR",0],["CREATIVE",0],["ADVENTURE",0]],"name":"NordicEraI","id":"NordicEraI"}],"player_uuid":"75a39539-384a-4c54-88c6-9e0454a7e90c","most_used_world":"NordicEraI (100%)","first_session":false,"mob_kills":0,"player_url_name":"MossyPickle16","afk_time":"0s","name":"Survival","player_kills":[],"end":"Aug 16 2021, 19:39","player_name":"MossyPickle16","world_series":[{"name":"NordicEraI","y":398848,"color":"#0099C6","drilldown":"NordicEraI"}],"server_url_name":"Survival","server_uuid":"89eae527-4566-404d-a8f5-88200718a4d7","deaths":0},{"server_name":"Survival","start":"Aug 16 2021, 19:18","length":"14m 17s","gm_series":[{"data":[["SURVIVAL",857005],["SPECTATOR",0],["CREATIVE",0],["ADVENTURE",0]],"name":"NordicEraI","id":"NordicEraI"}],"player_uuid":"75a39539-384a-4c54-88c6-9e0454a7e90c","most_used_world":"NordicEraI (100%)","first_session":false,"mob_kills":3,"player_url_name":"MossyPickle16","afk_time":"0s","name":"Survival","player_kills":[],"end":"Aug 16 2021, 19:32","player_name":"MossyPickle16","world_series":[{"name":"NordicEraI","y":857005,"color":"#0099C6","drilldown":"NordicEraI"}],"server_url_name":"Survival","server_uuid":"89eae527-4566-404d-a8f5-88200718a4d7","deaths":0},{"server_name":"Survival","start":"Aug 15 2021, 18:10","length":"19m 50s","gm_series":[{"data":[["SURVIVAL",1190777],["SPECTATOR",0],["CREATIVE",0],["ADVENTURE",0]],"name":"NordicEraI","id":"NordicEraI"}],"player_uuid":"75a39539-384a-4c54-88c6-9e0454a7e90c","most_used_world":"NordicEraI (100%)","first_session":false,"mob_kills":0,"player_url_name":"MossyPickle16","afk_time":"16m 50s","name":"Survival","player_kills":[],"end":"Aug 15 2021, 18:30","player_name":"MossyPickle16","world_series":[{"name":"NordicEraI","y":1190777,"color":"#0099C6","drilldown":"NordicEraI"}],"server_url_name":"Survival","server_uuid":"89eae527-4566-404d-a8f5-88200718a4d7","deaths":0},{"server_name":"Survival","start":"Aug 15 2021, 16:23","length":"11m 6s","gm_series":[{"data":[["SURVIVAL",666754],["SPECTATOR",0],["CREATIVE",0],["ADVENTURE",0]],"name":"NordicEraI","id":"NordicEraI"}],"player_uuid":"75a39539-384a-4c54-88c6-9e0454a7e90c","most_used_world":"NordicEraI (100%)","first_session":false,"mob_kills":1,"player_url_name":"MossyPickle16","afk_time":"0s","name":"Survival","player_kills":[],"end":"Aug 15 2021, 16:34","player_name":"MossyPickle16","world_series":[{"name":"NordicEraI","y":666754,"color":"#0099C6","drilldown":"NordicEraI"}],"server_url_name":"Survival","server_uuid":"89eae527-4566-404d-a8f5-88200718a4d7","deaths":0},{"server_name":"Survival","start":"Aug 15 2021, 15:11","length":"36m 1s","gm_series":[{"data":[["SURVIVAL",2161063],["SPECTATOR",0],["CREATIVE",0],["ADVENTURE",0]],"name":"NordicEraI","id":"NordicEraI"}],"player_uuid":"75a39539-384a-4c54-88c6-9e0454a7e90c","most_used_world":"NordicEraI (100%)","first_session":false,"mob_kills":0,"player_url_name":"MossyPickle16","afk_time":"33m 5s","name":"Survival","player_kills":[],"end":"Aug 15 2021, 15:47","player_name":"MossyPickle16","world_series":[{"name":"NordicEraI","y":2161063,"color":"#0099C6","drilldown":"NordicEraI"}],"server_url_name":"Survival","server_uuid":"89eae527-4566-404d-a8f5-88200718a4d7","deaths":0},{"server_name":"Survival","start":"Aug 13 2021, 17:50","length":"17s","gm_series":[{"data":[["SURVIVAL",17627],["SPECTATOR",0],["CREATIVE",0],["ADVENTURE",0]],"name":"NordicEraI","id":"NordicEraI"}],"player_uuid":"75a39539-384a-4c54-88c6-9e0454a7e90c","most_used_world":"NordicEraI (100%)","first_session":false,"mob_kills":0,"player_url_name":"MossyPickle16","afk_time":"0s","name":"Survival","player_kills":[],"end":"Aug 13 2021, 17:50","player_name":"MossyPickle16","world_series":[{"name":"NordicEraI","y":17627,"color":"#0099C6","drilldown":"NordicEraI"}],"server_url_name":"Survival","server_uuid":"89eae527-4566-404d-a8f5-88200718a4d7","deaths":0},{"server_name":"Survival","start":"Jul 23 2021, 12:58","length":"0s","gm_series":[{"data":[["SURVIVAL",380],["SPECTATOR",0],["CREATIVE",0],["ADVENTURE",0]],"name":"NordicEraI","id":"NordicEraI"}],"player_uuid":"75a39539-384a-4c54-88c6-9e0454a7e90c","most_used_world":"NordicEraI (100%)","first_session":false,"mob_kills":0,"player_url_name":"MossyPickle16","afk_time":"0s","name":"Survival","player_kills":[],"end":"Jul 23 2021, 12:58","player_name":"MossyPickle16","world_series":[{"name":"NordicEraI","y":380,"color":"#0099C6","drilldown":"NordicEraI"}],"server_url_name":"Survival","server_uuid":"89eae527-4566-404d-a8f5-88200718a4d7","deaths":0},{"server_name":"Survival","start":"Apr 5 2021, 22:39","length":"51s","gm_series":[{"data":[["SURVIVAL",51711],["SPECTATOR",0],["CREATIVE",0],["ADVENTURE",0]],"name":"NordicEraI","id":"NordicEraI"}],"player_uuid":"75a39539-384a-4c54-88c6-9e0454a7e90c","most_used_world":"NordicEraI (100%)","first_session":false,"mob_kills":0,"player_url_name":"MossyPickle16","afk_time":"0s","name":"Survival","player_kills":[],"end":"Apr 5 2021, 22:40","player_name":"MossyPickle16","world_series":[{"name":"NordicEraI","y":51711,"color":"#0099C6","drilldown":"NordicEraI"}],"server_url_name":"Survival","server_uuid":"89eae527-4566-404d-a8f5-88200718a4d7","deaths":0},{"server_name":"Survival","start":"Apr 2 2021, 16:49","length":"30m 48s","gm_series":[{"data":[["SURVIVAL",1848798],["SPECTATOR",0],["CREATIVE",0],["ADVENTURE",0]],"name":"NordicEraI","id":"NordicEraI"}],"player_uuid":"75a39539-384a-4c54-88c6-9e0454a7e90c","most_used_world":"NordicEraI (100%)","first_session":false,"mob_kills":0,"player_url_name":"MossyPickle16","afk_time":"0s","name":"Survival","player_kills":[],"end":"Apr 2 2021, 17:20","player_name":"MossyPickle16","world_series":[{"name":"NordicEraI","y":1848798,"color":"#0099C6","drilldown":"NordicEraI"}],"server_url_name":"Survival","server_uuid":"89eae527-4566-404d-a8f5-88200718a4d7","deaths":0},{"server_name":"Survival","start":"Apr 1 2021, 12:31","length":"16m 15s","gm_series":[{"data":[["SURVIVAL",975955],["SPECTATOR",0],["CREATIVE",0],["ADVENTURE",0]],"name":"NordicEraI","id":"NordicEraI"}],"player_uuid":"75a39539-384a-4c54-88c6-9e0454a7e90c","most_used_world":"NordicEraI (100%)","first_session":false,"mob_kills":0,"player_url_name":"MossyPickle16","afk_time":"0s","name":"Survival","player_kills":[],"end":"Apr 1 2021, 12:48","player_name":"MossyPickle16","world_series":[{"name":"NordicEraI","y":975955,"color":"#0099C6","drilldown":"NordicEraI"}],"server_url_name":"Survival","server_uuid":"89eae527-4566-404d-a8f5-88200718a4d7","deaths":0},{"server_name":"Survival","start":"Apr 1 2021, 11:15","length":"15m 30s","gm_series":[{"data":[["SURVIVAL",930787],["SPECTATOR",0],["CREATIVE",0],["ADVENTURE",0]],"name":"NordicEraI","id":"NordicEraI"}],"player_uuid":"75a39539-384a-4c54-88c6-9e0454a7e90c","most_used_world":"NordicEraI (100%)","first_session":false,"mob_kills":0,"player_url_name":"MossyPickle16","afk_time":"15m ","name":"Survival","player_kills":[],"end":"Apr 1 2021, 11:31","player_name":"MossyPickle16","world_series":[{"name":"NordicEraI","y":930787,"color":"#0099C6","drilldown":"NordicEraI"}],"server_url_name":"Survival","server_uuid":"89eae527-4566-404d-a8f5-88200718a4d7","deaths":0},{"server_name":"Survival","start":"Mar 31 2021, 23:39","length":"35m 58s","gm_series":[{"data":[["SURVIVAL",2158403],["SPECTATOR",0],["CREATIVE",0],["ADVENTURE",0]],"name":"NordicEraI","id":"NordicEraI"}],"player_uuid":"75a39539-384a-4c54-88c6-9e0454a7e90c","most_used_world":"NordicEraI (100%)","first_session":false,"mob_kills":1,"player_url_name":"MossyPickle16","afk_time":"0s","name":"Survival","player_kills":[],"end":"Apr 1 2021, 00:15","player_name":"MossyPickle16","world_series":[{"name":"NordicEraI","y":2158403,"color":"#0099C6","drilldown":"NordicEraI"}],"server_url_name":"Survival","server_uuid":"89eae527-4566-404d-a8f5-88200718a4d7","deaths":0},{"server_name":"Survival","start":"Mar 31 2021, 22:54","length":"40m 7s","gm_series":[{"data":[["SURVIVAL",2407753],["SPECTATOR",0],["CREATIVE",0],["ADVENTURE",0]],"name":"NordicEraI","id":"NordicEraI"}],"player_uuid":"75a39539-384a-4c54-88c6-9e0454a7e90c","most_used_world":"NordicEraI (100%)","first_session":false,"mob_kills":2,"player_url_name":"MossyPickle16","afk_time":"3m 15s","name":"Survival","player_kills":[],"end":"Mar 31 2021, 23:34","player_name":"MossyPickle16","world_series":[{"name":"NordicEraI","y":2407753,"color":"#0099C6","drilldown":"NordicEraI"}],"server_url_name":"Survival","server_uuid":"89eae527-4566-404d-a8f5-88200718a4d7","deaths":0},{"server_name":"Survival","start":"Mar 30 2021, 23:14","length":"41m 19s","gm_series":[{"data":[["SURVIVAL",2479225],["SPECTATOR",0],["CREATIVE",0],["ADVENTURE",0]],"name":"NordicEraI","id":"NordicEraI"}],"player_uuid":"75a39539-384a-4c54-88c6-9e0454a7e90c","most_used_world":"NordicEraI (100%)","first_session":false,"mob_kills":0,"player_url_name":"MossyPickle16","afk_time":"0s","name":"Survival","player_kills":[],"end":"Mar 30 2021, 23:56","player_name":"MossyPickle16","world_series":[{"name":"NordicEraI","y":2479225,"color":"#0099C6","drilldown":"NordicEraI"}],"server_url_name":"Survival","server_uuid":"89eae527-4566-404d-a8f5-88200718a4d7","deaths":1},{"server_name":"Survival","start":"Mar 30 2021, 23:12","length":"32s","gm_series":[{"data":[["SURVIVAL",32930],["SPECTATOR",0],["CREATIVE",0],["ADVENTURE",0]],"name":"NordicEraI","id":"NordicEraI"}],"player_uuid":"75a39539-384a-4c54-88c6-9e0454a7e90c","most_used_world":"NordicEraI (100%)","first_session":false,"mob_kills":0,"player_url_name":"MossyPickle16","afk_time":"0s","name":"Survival","player_kills":[],"end":"Mar 30 2021, 23:13","player_name":"MossyPickle16","world_series":[{"name":"NordicEraI","y":32930,"color":"#0099C6","drilldown":"NordicEraI"}],"server_url_name":"Survival","server_uuid":"89eae527-4566-404d-a8f5-88200718a4d7","deaths":0},{"server_name":"Survival","start":"Mar 30 2021, 23:08","length":"40s","gm_series":[{"data":[["SURVIVAL",40278],["SPECTATOR",0],["CREATIVE",0],["ADVENTURE",0]],"name":"NordicEraI","id":"NordicEraI"}],"player_uuid":"75a39539-384a-4c54-88c6-9e0454a7e90c","most_used_world":"NordicEraI (100%)","first_session":false,"mob_kills":0,"player_url_name":"MossyPickle16","afk_time":"0s","name":"Survival","player_kills":[],"end":"Mar 30 2021, 23:09","player_name":"MossyPickle16","world_series":[{"name":"NordicEraI","y":40278,"color":"#0099C6","drilldown":"NordicEraI"}],"server_url_name":"Survival","server_uuid":"89eae527-4566-404d-a8f5-88200718a4d7","deaths":0},{"server_name":"Survival","start":"Mar 30 2021, 21:39","length":"12m 52s","gm_series":[{"data":[["SURVIVAL",756600],["SPECTATOR",0],["CREATIVE",0],["ADVENTURE",0]],"name":"NordicEraI","id":"NordicEraI"},{"data":[["SURVIVAL",15647],["SPECTATOR",0],["CREATIVE",0],["ADVENTURE",0]],"name":"world_nether","id":"world_nether"}],"player_uuid":"75a39539-384a-4c54-88c6-9e0454a7e90c","most_used_world":"NordicEraI (97.97%)","first_session":false,"mob_kills":0,"player_url_name":"MossyPickle16","afk_time":"0s","name":"Survival","player_kills":[],"end":"Mar 30 2021, 21:51","player_name":"MossyPickle16","world_series":[{"name":"NordicEraI","y":756600,"color":"#0099C6","drilldown":"NordicEraI"},{"name":"world_nether","y":15647,"color":"#66AA00","drilldown":"world_nether"}],"server_url_name":"Survival","server_uuid":"89eae527-4566-404d-a8f5-88200718a4d7","deaths":0},{"server_name":"Survival","start":"Mar 30 2021, 20:57","length":"41m 9s","gm_series":[{"data":[["SURVIVAL",2469354],["SPECTATOR",0],["CREATIVE",0],["ADVENTURE",0]],"name":"NordicEraI","id":"NordicEraI"}],"player_uuid":"75a39539-384a-4c54-88c6-9e0454a7e90c","most_used_world":"NordicEraI (100%)","first_session":false,"mob_kills":0,"player_url_name":"MossyPickle16","afk_time":"0s","name":"Survival","player_kills":[],"end":"Mar 30 2021, 21:39","player_name":"MossyPickle16","world_series":[{"name":"NordicEraI","y":2469354,"color":"#0099C6","drilldown":"NordicEraI"}],"server_url_name":"Survival","server_uuid":"89eae527-4566-404d-a8f5-88200718a4d7","deaths":0},{"server_name":"Survival","start":"Mar 30 2021, 17:46","length":"20m 57s","gm_series":[{"data":[["SURVIVAL",1257015],["SPECTATOR",0],["CREATIVE",0],["ADVENTURE",0]],"name":"NordicEraI","id":"NordicEraI"}],"player_uuid":"75a39539-384a-4c54-88c6-9e0454a7e90c","most_used_world":"NordicEraI (100%)","first_session":false,"mob_kills":0,"player_url_name":"MossyPickle16","afk_time":"0s","name":"Survival","player_kills":[],"end":"Mar 30 2021, 18:07","player_name":"MossyPickle16","world_series":[{"name":"NordicEraI","y":1257015,"color":"#0099C6","drilldown":"NordicEraI"}],"server_url_name":"Survival","server_uuid":"89eae527-4566-404d-a8f5-88200718a4d7","deaths":0},{"server_name":"Survival","start":"Mar 30 2021, 15:45","length":"1h 58m 19s","gm_series":[{"data":[["SURVIVAL",7099237],["SPECTATOR",0],["CREATIVE",0],["ADVENTURE",0]],"name":"NordicEraI","id":"NordicEraI"}],"player_uuid":"75a39539-384a-4c54-88c6-9e0454a7e90c","most_used_world":"NordicEraI (100%)","first_session":false,"mob_kills":4,"player_url_name":"MossyPickle16","afk_time":"5m 11s","name":"Survival","player_kills":[],"end":"Mar 30 2021, 17:44","player_name":"MossyPickle16","world_series":[{"name":"NordicEraI","y":7099237,"color":"#0099C6","drilldown":"NordicEraI"}],"server_url_name":"Survival","server_uuid":"89eae527-4566-404d-a8f5-88200718a4d7","deaths":1},{"server_name":"Survival","start":"Mar 30 2021, 11:37","length":"2h 43m 27s","gm_series":[{"data":[["SURVIVAL",9807261],["SPECTATOR",0],["CREATIVE",0],["ADVENTURE",0]],"name":"NordicEraI","id":"NordicEraI"}],"player_uuid":"75a39539-384a-4c54-88c6-9e0454a7e90c","most_used_world":"NordicEraI (100%)","first_session":false,"mob_kills":22,"player_url_name":"MossyPickle16","afk_time":"0s","name":"Survival","player_kills":[],"end":"Mar 30 2021, 14:21","player_name":"MossyPickle16","world_series":[{"name":"NordicEraI","y":9807261,"color":"#0099C6","drilldown":"NordicEraI"}],"server_url_name":"Survival","server_uuid":"89eae527-4566-404d-a8f5-88200718a4d7","deaths":2},{"server_name":"Survival","start":"Mar 29 2021, 21:31","length":"2h 35m 32s","gm_series":[{"data":[["SURVIVAL",9332108],["SPECTATOR",0],["CREATIVE",0],["ADVENTURE",0]],"name":"NordicEraI","id":"NordicEraI"}],"player_uuid":"75a39539-384a-4c54-88c6-9e0454a7e90c","most_used_world":"NordicEraI (100%)","first_session":false,"mob_kills":9,"player_url_name":"MossyPickle16","afk_time":"0s","name":"Survival","player_kills":[],"end":"Mar 30 2021, 00:07","player_name":"MossyPickle16","world_series":[{"name":"NordicEraI","y":9332108,"color":"#0099C6","drilldown":"NordicEraI"}],"server_url_name":"Survival","server_uuid":"89eae527-4566-404d-a8f5-88200718a4d7","deaths":11},{"server_name":"Survival","start":"Mar 4 2021, 14:39","length":"7m 32s","gm_series":[{"data":[["SURVIVAL",452495],["SPECTATOR",0],["CREATIVE",0],["ADVENTURE",0]],"name":"NordicEraI","id":"NordicEraI"}],"player_uuid":"75a39539-384a-4c54-88c6-9e0454a7e90c","most_used_world":"NordicEraI (100%)","first_session":false,"mob_kills":0,"player_url_name":"MossyPickle16","afk_time":"0s","name":"Survival","player_kills":[],"end":"Mar 4 2021, 14:46","player_name":"MossyPickle16","world_series":[{"name":"NordicEraI","y":452495,"color":"#0099C6","drilldown":"NordicEraI"}],"server_url_name":"Survival","server_uuid":"89eae527-4566-404d-a8f5-88200718a4d7","deaths":1},{"server_name":"Survival","start":"Mar 4 2021, 14:02","length":"1m 13s","gm_series":[{"data":[["SURVIVAL",73806],["SPECTATOR",0],["CREATIVE",0],["ADVENTURE",0]],"name":"NordicEraI","id":"NordicEraI"}],"player_uuid":"75a39539-384a-4c54-88c6-9e0454a7e90c","most_used_world":"NordicEraI (100%)","first_session":false,"mob_kills":1,"player_url_name":"MossyPickle16","afk_time":"0s","name":"Survival","player_kills":[],"end":"Mar 4 2021, 14:04","player_name":"MossyPickle16","world_series":[{"name":"NordicEraI","y":73806,"color":"#0099C6","drilldown":"NordicEraI"}],"server_url_name":"Survival","server_uuid":"89eae527-4566-404d-a8f5-88200718a4d7","deaths":1},{"server_name":"Survival","start":"Mar 4 2021, 14:01","length":"44s","gm_series":[{"data":[["SURVIVAL",44919],["SPECTATOR",0],["CREATIVE",0],["ADVENTURE",0]],"name":"NordicEraI","id":"NordicEraI"}],"player_uuid":"75a39539-384a-4c54-88c6-9e0454a7e90c","most_used_world":"NordicEraI (100%)","first_session":true,"mob_kills":0,"player_url_name":"MossyPickle16","afk_time":"0s","name":"Survival","player_kills":[],"end":"Mar 4 2021, 14:01","player_name":"MossyPickle16","world_series":[{"name":"NordicEraI","y":44919,"color":"#0099C6","drilldown":"NordicEraI"}],"server_url_name":"Survival","server_uuid":"89eae527-4566-404d-a8f5-88200718a4d7","deaths":0}],"calendar_series":[{"title":"Registered: Mar 4 2021, 14:01","start":1614862860446,"color":"#8BC34A"},{"title":"Playtime: 9m 31s","start":"2021-03-04","color":"#4CAF50"},{"title":"Sessions: 3","start":"2021-03-04"},{"title":"Playtime: 51s","start":"2021-04-05","color":"#4CAF50"},{"title":"Sessions: 1","start":"2021-04-05"},{"title":"Playtime: 30m 48s","start":"2021-04-02","color":"#4CAF50"},{"title":"Sessions: 1","start":"2021-04-02"},{"title":"Playtime: 31m 46s","start":"2021-04-01","color":"#4CAF50"},{"title":"Sessions: 2","start":"2021-04-01"},{"title":"Playtime: 0s","start":"2021-07-23","color":"#4CAF50"},{"title":"Sessions: 1","start":"2021-07-23"},{"title":"Playtime: 17s","start":"2021-08-13","color":"#4CAF50"},{"title":"Sessions: 1","start":"2021-08-13"},{"title":"Playtime: 1h 16m 6s","start":"2021-03-31","color":"#4CAF50"},{"title":"Sessions: 2","start":"2021-03-31"},{"title":"Playtime: 6h 39m 17s","start":"2021-03-30","color":"#4CAF50"},{"title":"Sessions: 8","start":"2021-03-30"},{"title":"Playtime: 1h 6m 58s","start":"2021-08-15","color":"#4CAF50"},{"title":"Sessions: 3","start":"2021-08-15"},{"title":"Playtime: 39m 54s","start":"2021-08-16","color":"#4CAF50"},{"title":"Sessions: 3","start":"2021-08-16"},{"title":"Playtime: 4s","start":"2021-08-18","color":"#4CAF50"},{"title":"Sessions: 1","start":"2021-08-18"},{"title":"Playtime: 2h 35m 32s","start":"2021-03-29","color":"#4CAF50"},{"title":"Sessions: 1","start":"2021-03-29"},{"title":"Session: 4s","start":1629292578666,"end":1629292583257},{"title":"Session: 18m 58s","start":1629143812816,"end":1629144951222},{"title":"Session: 6m 38s","start":1629142370417,"end":1629142769265},{"title":"Session: 14m 17s","start":1629141496929,"end":1629142353934},{"title":"Session: 19m 50s","start":1629051015094,"end":1629052205871},{"title":"Session: 11m 6s","start":1629044610618,"end":1629045277372},{"title":"Session: 36m 1s","start":1629040262650,"end":1629042423713},{"title":"Session: 17s","start":1628877006741,"end":1628877024368},{"title":"Session: 0s","start":1627045112245,"end":1627045112625},{"title":"Session: 51s","start":1617662399585,"end":1617662451296},{"title":"Session: 30m 48s","start":1617382185840,"end":1617384034638},{"title":"Session: 16m 15s","start":1617280309311,"end":1617281285266},{"title":"Session: 15m 30s","start":1617275738090,"end":1617276668877},{"title":"Session: 35m 58s","start":1617233996175,"end":1617236154578},{"title":"Session: 40m 7s","start":1617231264745,"end":1617233672498},{"title":"Session: 41m 19s","start":1617146086975,"end":1617148566200},{"title":"Session: 32s","start":1617145953261,"end":1617145986191},{"title":"Session: 40s","start":1617145736272,"end":1617145776550},{"title":"Session: 12m 52s","start":1617140347402,"end":1617141119649},{"title":"Session: 41m 9s","start":1617137876240,"end":1617140345594},{"title":"Session: 20m 57s","start":1617126418927,"end":1617127675942},{"title":"Session: 1h 58m 19s","start":1617119150130,"end":1617126249367},{"title":"Session: 2h 43m 27s","start":1617104262047,"end":1617114069308},{"title":"Session: 2h 35m 32s","start":1617053515006,"end":1617062847114},{"title":"Session: 7m 32s","start":1614868742711,"end":1614869195206},{"title":"Session: 1m 13s","start":1614866574823,"end":1614866648629},{"title":"Session: 44s","start":1614866460494,"end":1614866505413}],"player_deaths":[],"gm_series":[{"data":[["SURVIVAL",48654086],["SPECTATOR",0],["CREATIVE",0],["ADVENTURE",0]],"name":"NordicEraI","id":"NordicEraI"},{"data":[["SURVIVAL",15647],["SPECTATOR",0],["CREATIVE",0],["ADVENTURE",0]],"name":"world_nether","id":"world_nether"}],"world_pie_series":[{"name":"NordicEraI","y":48654086,"color":"#0099C6","drilldown":"NordicEraI"},{"name":"world_nether","y":15647,"color":"#66AA00","drilldown":"world_nether"}],"server_pie_colors":["#0099C6","#66AA00","#316395","#994499","#22AA99","#AAAA11","#6633CC","#E67300","#329262","#5574A6"],"servers":[{"server_name":"Survival","last_seen":"Aug 18 2021, 13:16","registered":"Mar 4 2021, 14:01","gm_series":[{"data":[["SURVIVAL",48654086],["SPECTATOR",0],["CREATIVE",0],["ADVENTURE",0]],"name":"NordicEraI","id":"NordicEraI"},{"data":[["SURVIVAL",15647],["SPECTATOR",0],["CREATIVE",0],["ADVENTURE",0]],"name":"world_nether","id":"world_nether"}],"playtime":"13h 31m 9s","session_median":"15m 30s","world_pie_series":[{"name":"NordicEraI","y":48654086,"color":"#0099C6","drilldown":"NordicEraI"},{"name":"world_nether","y":15647,"color":"#66AA00","drilldown":"world_nether"}],"operator":false,"mob_kills":43,"afk_time":"1h 13m 24s","session_count":27,"player_kills":0,"longest_session_length":"2h 43m 27s","banned":false,"deaths":17}],"server_pie_series":[{"name":"Survival","y":48669733}],"online_activity":{"session_count_30d":0,"session_count_7d":0,"afk_time_7d":"0s","mob_kill_count_30d":0,"active_playtime_7d":"0s","mob_kill_count_7d":0,"afk_time_30d":"0s","average_session_length_30d":"0s","death_count_30d":0,"active_playtime_30d":"0s","average_session_length_7d":"0s","median_session_length_7d":"-","median_session_length_30d":"-","playtime_30d":"0s","player_kill_count_30d":0,"death_count_7d":0,"playtime_7d":"0s","player_kill_count_7d":0},"player_kills":[],"sessions_per_page":50,"punchcard_series":[{"x":0,"y":0,"z":0,"marker":{"radius":0}},{"x":3600000,"y":0,"z":0,"marker":{"radius":0}},{"x":7200000,"y":0,"z":0,"marker":{"radius":0}},{"x":10800000,"y":0,"z":0,"marker":{"radius":0}},{"x":14400000,"y":0,"z":0,"marker":{"radius":0}},{"x":18000000,"y":0,"z":0,"marker":{"radius":0}},{"x":21600000,"y":0,"z":0,"marker":{"radius":0}},{"x":25200000,"y":0,"z":0,"marker":{"radius":0}},{"x":28800000,"y":0,"z":0,"marker":{"radius":0}},{"x":32400000,"y":0,"z":0,"marker":{"radius":0}},{"x":36000000,"y":0,"z":0,"marker":{"radius":0}},{"x":39600000,"y":0,"z":0,"marker":{"radius":0}},{"x":43200000,"y":0,"z":0,"marker":{"radius":0}},{"x":46800000,"y":0,"z":0,"marker":{"radius":0}},{"x":50400000,"y":0,"z":0,"marker":{"radius":0}},{"x":54000000,"y":0,"z":0,"marker":{"radius":0}},{"x":57600000,"y":0,"z":0,"marker":{"radius":0}},{"x":61200000,"y":0,"z":0,"marker":{"radius":0}},{"x":64800000,"y":0,"z":0,"marker":{"radius":0}},{"x":68400000,"y":0,"z":14,"marker":{"radius":14}},{"x":72000000,"y":0,"z":0,"marker":{"radius":0}},{"x":75600000,"y":0,"z":7,"marker":{"radius":7}},{"x":79200000,"y":0,"z":7,"marker":{"radius":7}},{"x":82800000,"y":0,"z":0,"marker":{"radius":0}},{"x":0,"y":1,"z":0,"marker":{"radius":0}},{"x":3600000,"y":1,"z":0,"marker":{"radius":0}},{"x":7200000,"y":1,"z":0,"marker":{"radius":0}},{"x":10800000,"y":1,"z":0,"marker":{"radius":0}},{"x":14400000,"y":1,"z":0,"marker":{"radius":0}},{"x":18000000,"y":1,"z":0,"marker":{"radius":0}},{"x":21600000,"y":1,"z":0,"marker":{"radius":0}},{"x":25200000,"y":1,"z":0,"marker":{"radius":0}},{"x":28800000,"y":1,"z":0,"marker":{"radius":0}},{"x":32400000,"y":1,"z":0,"marker":{"radius":0}},{"x":36000000,"y":1,"z":0,"marker":{"radius":0}},{"x":39600000,"y":1,"z":7,"marker":{"radius":7}},{"x":43200000,"y":1,"z":0,"marker":{"radius":0}},{"x":46800000,"y":1,"z":0,"marker":{"radius":0}},{"x":50400000,"y":1,"z":0,"marker":{"radius":0}},{"x":54000000,"y":1,"z":7,"marker":{"radius":7}},{"x":57600000,"y":1,"z":0,"marker":{"radius":0}},{"x":61200000,"y":1,"z":7,"marker":{"radius":7}},{"x":64800000,"y":1,"z":0,"marker":{"radius":0}},{"x":68400000,"y":1,"z":0,"marker":{"radius":0}},{"x":72000000,"y":1,"z":7,"marker":{"radius":7}},{"x":75600000,"y":1,"z":7,"marker":{"radius":7}},{"x":79200000,"y":1,"z":0,"marker":{"radius":0}},{"x":82800000,"y":1,"z":14,"marker":{"radius":14}},{"x":0,"y":2,"z":0,"marker":{"radius":0}},{"x":3600000,"y":2,"z":0,"marker":{"radius":0}},{"x":7200000,"y":2,"z":0,"marker":{"radius":0}},{"x":10800000,"y":2,"z":0,"marker":{"radius":0}},{"x":14400000,"y":2,"z":0,"marker":{"radius":0}},{"x":18000000,"y":2,"z":0,"marker":{"radius":0}},{"x":21600000,"y":2,"z":0,"marker":{"radius":0}},{"x":25200000,"y":2,"z":0,"marker":{"radius":0}},{"x":28800000,"y":2,"z":0,"marker":{"radius":0}},{"x":32400000,"y":2,"z":0,"marker":{"radius":0}},{"x":36000000,"y":2,"z":0,"marker":{"radius":0}},{"x":39600000,"y":2,"z":0,"marker":{"radius":0}},{"x":43200000,"y":2,"z":0,"marker":{"radius":0}},{"x":46800000,"y":2,"z":7,"marker":{"radius":7}},{"x":50400000,"y":2,"z":0,"marker":{"radius":0}},{"x":54000000,"y":2,"z":0,"marker":{"radius":0}},{"x":57600000,"y":2,"z":0,"marker":{"radius":0}},{"x":61200000,"y":2,"z":0,"marker":{"radius":0}},{"x":64800000,"y":2,"z":0,"marker":{"radius":0}},{"x":68400000,"y":2,"z":0,"marker":{"radius":0}},{"x":72000000,"y":2,"z":0,"marker":{"radius":0}},{"x":75600000,"y":2,"z":0,"marker":{"radius":0}},{"x":79200000,"y":2,"z":7,"marker":{"radius":7}},{"x":82800000,"y":2,"z":7,"marker":{"radius":7}},{"x":0,"y":3,"z":0,"marker":{"radius":0}},{"x":3600000,"y":3,"z":0,"marker":{"radius":0}},{"x":7200000,"y":3,"z":0,"marker":{"radius":0}},{"x":10800000,"y":3,"z":0,"marker":{"radius":0}},{"x":14400000,"y":3,"z":0,"marker":{"radius":0}},{"x":18000000,"y":3,"z":0,"marker":{"radius":0}},{"x":21600000,"y":3,"z":0,"marker":{"radius":0}},{"x":25200000,"y":3,"z":0,"marker":{"radius":0}},{"x":28800000,"y":3,"z":0,"marker":{"radius":0}},{"x":32400000,"y":3,"z":0,"marker":{"radius":0}},{"x":36000000,"y":3,"z":0,"marker":{"radius":0}},{"x":39600000,"y":3,"z":7,"marker":{"radius":7}},{"x":43200000,"y":3,"z":7,"marker":{"radius":7}},{"x":46800000,"y":3,"z":0,"marker":{"radius":0}},{"x":50400000,"y":3,"z":14,"marker":{"radius":14}},{"x":54000000,"y":3,"z":0,"marker":{"radius":0}},{"x":57600000,"y":3,"z":0,"marker":{"radius":0}},{"x":61200000,"y":3,"z":0,"marker":{"radius":0}},{"x":64800000,"y":3,"z":0,"marker":{"radius":0}},{"x":68400000,"y":3,"z":0,"marker":{"radius":0}},{"x":72000000,"y":3,"z":0,"marker":{"radius":0}},{"x":75600000,"y":3,"z":0,"marker":{"radius":0}},{"x":79200000,"y":3,"z":0,"marker":{"radius":0}},{"x":82800000,"y":3,"z":0,"marker":{"radius":0}},{"x":0,"y":4,"z":0,"marker":{"radius":0}},{"x":3600000,"y":4,"z":0,"marker":{"radius":0}},{"x":7200000,"y":4,"z":0,"marker":{"radius":0}},{"x":10800000,"y":4,"z":0,"marker":{"radius":0}},{"x":14400000,"y":4,"z":0,"marker":{"radius":0}},{"x":18000000,"y":4,"z":0,"marker":{"radius":0}},{"x":21600000,"y":4,"z":0,"marker":{"radius":0}},{"x":25200000,"y":4,"z":0,"marker":{"radius":0}},{"x":28800000,"y":4,"z":0,"marker":{"radius":0}},{"x":32400000,"y":4,"z":0,"marker":{"radius":0}},{"x":36000000,"y":4,"z":0,"marker":{"radius":0}},{"x":39600000,"y":4,"z":0,"marker":{"radius":0}},{"x":43200000,"y":4,"z":7,"marker":{"radius":7}},{"x":46800000,"y":4,"z":0,"marker":{"radius":0}},{"x":50400000,"y":4,"z":0,"marker":{"radius":0}},{"x":54000000,"y":4,"z":0,"marker":{"radius":0}},{"x":57600000,"y":4,"z":7,"marker":{"radius":7}},{"x":61200000,"y":4,"z":7,"marker":{"radius":7}},{"x":64800000,"y":4,"z":0,"marker":{"radius":0}},{"x":68400000,"y":4,"z":0,"marker":{"radius":0}},{"x":72000000,"y":4,"z":0,"marker":{"radius":0}},{"x":75600000,"y":4,"z":0,"marker":{"radius":0}},{"x":79200000,"y":4,"z":0,"marker":{"radius":0}},{"x":82800000,"y":4,"z":0,"marker":{"radius":0}},{"x":0,"y":5,"z":0,"marker":{"radius":0}},{"x":3600000,"y":5,"z":0,"marker":{"radius":0}},{"x":7200000,"y":5,"z":0,"marker":{"radius":0}},{"x":10800000,"y":5,"z":0,"marker":{"radius":0}},{"x":14400000,"y":5,"z":0,"marker":{"radius":0}},{"x":18000000,"y":5,"z":0,"marker":{"radius":0}},{"x":21600000,"y":5,"z":0,"marker":{"radius":0}},{"x":25200000,"y":5,"z":0,"marker":{"radius":0}},{"x":28800000,"y":5,"z":0,"marker":{"radius":0}},{"x":32400000,"y":5,"z":0,"marker":{"radius":0}},{"x":36000000,"y":5,"z":0,"marker":{"radius":0}},{"x":39600000,"y":5,"z":0,"marker":{"radius":0}},{"x":43200000,"y":5,"z":0,"marker":{"radius":0}},{"x":46800000,"y":5,"z":0,"marker":{"radius":0}},{"x":50400000,"y":5,"z":0,"marker":{"radius":0}},{"x":54000000,"y":5,"z":0,"marker":{"radius":0}},{"x":57600000,"y":5,"z":0,"marker":{"radius":0}},{"x":61200000,"y":5,"z":0,"marker":{"radius":0}},{"x":64800000,"y":5,"z":0,"marker":{"radius":0}},{"x":68400000,"y":5,"z":0,"marker":{"radius":0}},{"x":72000000,"y":5,"z":0,"marker":{"radius":0}},{"x":75600000,"y":5,"z":0,"marker":{"radius":0}},{"x":79200000,"y":5,"z":0,"marker":{"radius":0}},{"x":82800000,"y":5,"z":0,"marker":{"radius":0}},{"x":0,"y":6,"z":0,"marker":{"radius":0}},{"x":3600000,"y":6,"z":0,"marker":{"radius":0}},{"x":7200000,"y":6,"z":0,"marker":{"radius":0}},{"x":10800000,"y":6,"z":0,"marker":{"radius":0}},{"x":14400000,"y":6,"z":0,"marker":{"radius":0}},{"x":18000000,"y":6,"z":0,"marker":{"radius":0}},{"x":21600000,"y":6,"z":0,"marker":{"radius":0}},{"x":25200000,"y":6,"z":0,"marker":{"radius":0}},{"x":28800000,"y":6,"z":0,"marker":{"radius":0}},{"x":32400000,"y":6,"z":0,"marker":{"radius":0}},{"x":36000000,"y":6,"z":0,"marker":{"radius":0}},{"x":39600000,"y":6,"z":0,"marker":{"radius":0}},{"x":43200000,"y":6,"z":0,"marker":{"radius":0}},{"x":46800000,"y":6,"z":0,"marker":{"radius":0}},{"x":50400000,"y":6,"z":0,"marker":{"radius":0}},{"x":54000000,"y":6,"z":7,"marker":{"radius":7}},{"x":57600000,"y":6,"z":7,"marker":{"radius":7}},{"x":61200000,"y":6,"z":0,"marker":{"radius":0}},{"x":64800000,"y":6,"z":7,"marker":{"radius":7}},{"x":68400000,"y":6,"z":0,"marker":{"radius":0}},{"x":72000000,"y":6,"z":0,"marker":{"radius":0}},{"x":75600000,"y":6,"z":0,"marker":{"radius":0}},{"x":79200000,"y":6,"z":0,"marker":{"radius":0}},{"x":82800000,"y":6,"z":0,"marker":{"radius":0}}],"nicknames":[{"nickname":"x<span class=\"yellow\"><span class=\"gold\"><span class=\"blue\"><span class=\"darkgreen\"><span class=\"blue\"><span class=\"gold\">Mx<span class=\"pink\"><span class=\"darkred\"><span class=\"blue\"><span class=\"gray\"><span class=\"blue\"><span class=\"yellow\">ox<span class=\"red\"><span class=\"darkgreen\"><span class=\"blue\"><span class=\"red\"><span class=\"green\"><span class=\"gold\">sx<span class=\"aqua\"><span class=\"black\"><span class=\"green\"><span class=\"darkgreen\"><span class=\"green\"><span class=\"yellow\">sx<span class=\"blue\"><span class=\"yellow\"><span class=\"green\"><span class=\"gray\"><span class=\"aqua\"><span class=\"gold\"></span></span></span></span></span></span></span></span></span></span></span></span></span></span></span></span></span></span></span></span></span></span></span></span></span></span></span></span></span></span>","server":"Survival","date":"Aug 16 2021, 19:38"},{"nickname":"MossyPickle16","server":"Survival","date":"Mar 30 2021, 12:33"}],"connections":[{"geolocation":"United Kingdom","date":"Aug 18 2021, 13:16"}],"info":{"kick_count":1,"last_seen":"Aug 18 2021, 13:16","favorite_server":"Survival","mob_kill_count":43,"player_kill_count":0,"registered":"Mar 4 2021, 14:01","activity_index_group":"Inactive","playtime":"13h 31m 9s","session_median":"15m 30s","active_playtime":"12h 17m 45s","operator":false,"afk_time":"1h 13m 24s","death_count":17,"worst_ping":"Unavailable","session_count":27,"online":false,"longest_session_length":"2h 43m 27s","best_ping":"Unavailable","banned":false,"activity_index":"0","average_ping":"Unavailable"},"first_day":1}