{"kill_data":{"deaths_7d":0,"mob_deaths_7d":0,"mob_kills_total":803,"player_kdr_30d":"0","player_kills_7d":0,"player_deaths_total":0,"deaths_30d":0,"deaths_total":7,"player_kills_total":0,"mob_deaths_30d":0,"player_deaths_30d":0,"mob_kdr_30d":"0","player_kdr_total":"0","weapon_3rd":"-","mob_kdr_7d":"0","player_kdr_7d":"0","player_kills_30d":0,"weapon_2nd":"-","player_deaths_7d":0,"mob_deaths_total":7,"mob_kills_7d":0,"mob_kdr_total":"114.71","weapon_1st":"-","mob_kills_30d":0},"sessions":[{"server_name":"Survival","start":"Jul 26 2021, 19:30","length":"11m 26s","gm_series":[{"data":[["SURVIVAL",686098],["SPECTATOR",0],["CREATIVE",0],["ADVENTURE",0]],"name":"NordicEraI","id":"NordicEraI"}],"player_uuid":"4fefb418-f03c-46f2-bb0e-7a8e2d1c00ee","most_used_world":"NordicEraI (100%)","first_session":false,"mob_kills":1,"player_url_name":"Robberdrup","afk_time":"3m 27s","name":"Survival","player_kills":[],"end":"Jul 26 2021, 19:42","player_name":"Robberdrup","world_series":[{"name":"NordicEraI","y":686098,"color":"#0099C6","drilldown":"NordicEraI"}],"server_url_name":"Survival","server_uuid":"89eae527-4566-404d-a8f5-88200718a4d7","deaths":0},{"server_name":"Survival","start":"Jul 16 2021, 22:08","length":"38m 36s","gm_series":[{"data":[["SURVIVAL",2316328],["SPECTATOR",0],["CREATIVE",0],["ADVENTURE",0]],"name":"NordicEraI","id":"NordicEraI"}],"player_uuid":"4fefb418-f03c-46f2-bb0e-7a8e2d1c00ee","most_used_world":"NordicEraI (100%)","first_session":false,"mob_kills":27,"player_url_name":"Robberdrup","afk_time":"0s","name":"Survival","player_kills":[],"end":"Jul 16 2021, 22:46","player_name":"Robberdrup","world_series":[{"name":"NordicEraI","y":2316328,"color":"#0099C6","drilldown":"NordicEraI"}],"server_url_name":"Survival","server_uuid":"89eae527-4566-404d-a8f5-88200718a4d7","deaths":0},{"server_name":"Survival","start":"Jul 16 2021, 17:49","length":"39m 59s","gm_series":[{"data":[["SURVIVAL",746716],["SPECTATOR",0],["CREATIVE",0],["ADVENTURE",0]],"name":"NordicEraI","id":"NordicEraI"},{"data":[["SURVIVAL",1652362],["SPECTATOR",0],["CREATIVE",0],["ADVENTURE",0]],"name":"world_nether","id":"world_nether"}],"player_uuid":"4fefb418-f03c-46f2-bb0e-7a8e2d1c00ee","most_used_world":"world_nether (68.87%)","first_session":false,"mob_kills":18,"player_url_name":"Robberdrup","afk_time":"0s","name":"Survival","player_kills":[],"end":"Jul 16 2021, 18:29","player_name":"Robberdrup","world_series":[{"name":"NordicEraI","y":746716,"color":"#0099C6","drilldown":"NordicEraI"},{"name":"world_nether","y":1652362,"color":"#66AA00","drilldown":"world_nether"}],"server_url_name":"Survival","server_uuid":"89eae527-4566-404d-a8f5-88200718a4d7","deaths":2},{"server_name":"Survival","start":"Jul 16 2021, 13:20","length":"1h 19m 57s","gm_series":[{"data":[["SURVIVAL",4797432],["SPECTATOR",0],["CREATIVE",0],["ADVENTURE",0]],"name":"NordicEraI","id":"NordicEraI"}],"player_uuid":"4fefb418-f03c-46f2-bb0e-7a8e2d1c00ee","most_used_world":"NordicEraI (100%)","first_session":false,"mob_kills":27,"player_url_name":"Robberdrup","afk_time":"3m 27s","name":"Survival","player_kills":[],"end":"Jul 16 2021, 14:39","player_name":"Robberdrup","world_series":[{"name":"NordicEraI","y":4797432,"color":"#0099C6","drilldown":"NordicEraI"}],"server_url_name":"Survival","server_uuid":"89eae527-4566-404d-a8f5-88200718a4d7","deaths":0},{"server_name":"Survival","start":"Jul 15 2021, 22:40","length":"1h 18m 29s","gm_series":[{"data":[["SURVIVAL",4709389],["SPECTATOR",0],["CREATIVE",0],["ADVENTURE",0]],"name":"NordicEraI","id":"NordicEraI"}],"player_uuid":"4fefb418-f03c-46f2-bb0e-7a8e2d1c00ee","most_used_world":"NordicEraI (100%)","first_session":false,"mob_kills":21,"player_url_name":"Robberdrup","afk_time":"0s","name":"Survival","player_kills":[],"end":"Jul 15 2021, 23:59","player_name":"Robberdrup","world_series":[{"name":"NordicEraI","y":4709389,"color":"#0099C6","drilldown":"NordicEraI"}],"server_url_name":"Survival","server_uuid":"89eae527-4566-404d-a8f5-88200718a4d7","deaths":0},{"server_name":"Survival","start":"Jul 14 2021, 21:38","length":"2h 5m 44s","gm_series":[{"data":[["SURVIVAL",7544684],["SPECTATOR",0],["CREATIVE",0],["ADVENTURE",0]],"name":"NordicEraI","id":"NordicEraI"}],"player_uuid":"4fefb418-f03c-46f2-bb0e-7a8e2d1c00ee","most_used_world":"NordicEraI (100%)","first_session":false,"mob_kills":34,"player_url_name":"Robberdrup","afk_time":"0s","name":"Survival","player_kills":[],"end":"Jul 14 2021, 23:43","player_name":"Robberdrup","world_series":[{"name":"NordicEraI","y":7544684,"color":"#0099C6","drilldown":"NordicEraI"}],"server_url_name":"Survival","server_uuid":"89eae527-4566-404d-a8f5-88200718a4d7","deaths":0},{"server_name":"Survival","start":"Jul 14 2021, 21:32","length":"5m 50s","gm_series":[{"data":[["SURVIVAL",350596],["SPECTATOR",0],["CREATIVE",0],["ADVENTURE",0]],"name":"NordicEraI","id":"NordicEraI"}],"player_uuid":"4fefb418-f03c-46f2-bb0e-7a8e2d1c00ee","most_used_world":"NordicEraI (100%)","first_session":false,"mob_kills":2,"player_url_name":"Robberdrup","afk_time":"0s","name":"Survival","player_kills":[],"end":"Jul 14 2021, 21:37","player_name":"Robberdrup","world_series":[{"name":"NordicEraI","y":350596,"color":"#0099C6","drilldown":"NordicEraI"}],"server_url_name":"Survival","server_uuid":"89eae527-4566-404d-a8f5-88200718a4d7","deaths":0},{"server_name":"Survival","start":"Jul 14 2021, 20:31","length":"1h 22s","gm_series":[{"data":[["SURVIVAL",2964775],["SPECTATOR",0],["CREATIVE",0],["ADVENTURE",0]],"name":"NordicEraI","id":"NordicEraI"},{"data":[["SURVIVAL",657796],["SPECTATOR",0],["CREATIVE",0],["ADVENTURE",0]],"name":"world_nether","id":"world_nether"}],"player_uuid":"4fefb418-f03c-46f2-bb0e-7a8e2d1c00ee","most_used_world":"NordicEraI (81.84%)","first_session":false,"mob_kills":8,"player_url_name":"Robberdrup","afk_time":"0s","name":"Survival","player_kills":[],"end":"Jul 14 2021, 21:32","player_name":"Robberdrup","world_series":[{"name":"NordicEraI","y":2964775,"color":"#0099C6","drilldown":"NordicEraI"},{"name":"world_nether","y":657796,"color":"#66AA00","drilldown":"world_nether"}],"server_url_name":"Survival","server_uuid":"89eae527-4566-404d-a8f5-88200718a4d7","deaths":1},{"server_name":"Survival","start":"Jul 14 2021, 20:19","length":"12m 11s","gm_series":[{"data":[["SURVIVAL",731489],["SPECTATOR",0],["CREATIVE",0],["ADVENTURE",0]],"name":"NordicEraI","id":"NordicEraI"}],"player_uuid":"4fefb418-f03c-46f2-bb0e-7a8e2d1c00ee","most_used_world":"NordicEraI (100%)","first_session":false,"mob_kills":10,"player_url_name":"Robberdrup","afk_time":"0s","name":"Survival","player_kills":[],"end":"Jul 14 2021, 20:31","player_name":"Robberdrup","world_series":[{"name":"NordicEraI","y":731489,"color":"#0099C6","drilldown":"NordicEraI"}],"server_url_name":"Survival","server_uuid":"89eae527-4566-404d-a8f5-88200718a4d7","deaths":0},{"server_name":"Survival","start":"Jul 14 2021, 15:24","length":"10m 1s","gm_series":[{"data":[["SURVIVAL",601576],["SPECTATOR",0],["CREATIVE",0],["ADVENTURE",0]],"name":"NordicEraI","id":"NordicEraI"}],"player_uuid":"4fefb418-f03c-46f2-bb0e-7a8e2d1c00ee","most_used_world":"NordicEraI (100%)","first_session":false,"mob_kills":8,"player_url_name":"Robberdrup","afk_time":"0s","name":"Survival","player_kills":[],"end":"Jul 14 2021, 15:34","player_name":"Robberdrup","world_series":[{"name":"NordicEraI","y":601576,"color":"#0099C6","drilldown":"NordicEraI"}],"server_url_name":"Survival","server_uuid":"89eae527-4566-404d-a8f5-88200718a4d7","deaths":0},{"server_name":"Survival","start":"Jul 14 2021, 11:13","length":"40m 8s","gm_series":[{"data":[["SURVIVAL",2408942],["SPECTATOR",0],["CREATIVE",0],["ADVENTURE",0]],"name":"NordicEraI","id":"NordicEraI"}],"player_uuid":"4fefb418-f03c-46f2-bb0e-7a8e2d1c00ee","most_used_world":"NordicEraI (100%)","first_session":false,"mob_kills":12,"player_url_name":"Robberdrup","afk_time":"0s","name":"Survival","player_kills":[],"end":"Jul 14 2021, 11:54","player_name":"Robberdrup","world_series":[{"name":"NordicEraI","y":2408942,"color":"#0099C6","drilldown":"NordicEraI"}],"server_url_name":"Survival","server_uuid":"89eae527-4566-404d-a8f5-88200718a4d7","deaths":0},{"server_name":"Survival","start":"Jul 14 2021, 09:49","length":"47m 19s","gm_series":[{"data":[["SURVIVAL",2839848],["SPECTATOR",0],["CREATIVE",0],["ADVENTURE",0]],"name":"NordicEraI","id":"NordicEraI"}],"player_uuid":"4fefb418-f03c-46f2-bb0e-7a8e2d1c00ee","most_used_world":"NordicEraI (100%)","first_session":false,"mob_kills":4,"player_url_name":"Robberdrup","afk_time":"0s","name":"Survival","player_kills":[],"end":"Jul 14 2021, 10:36","player_name":"Robberdrup","world_series":[{"name":"NordicEraI","y":2839848,"color":"#0099C6","drilldown":"NordicEraI"}],"server_url_name":"Survival","server_uuid":"89eae527-4566-404d-a8f5-88200718a4d7","deaths":0},{"server_name":"Survival","start":"Jul 13 2021, 21:06","length":"1h 22m 28s","gm_series":[{"data":[["SURVIVAL",4170854],["SPECTATOR",0],["CREATIVE",0],["ADVENTURE",0]],"name":"NordicEraI","id":"NordicEraI"},{"data":[["SURVIVAL",777932],["SPECTATOR",0],["CREATIVE",0],["ADVENTURE",0]],"name":"world_nether","id":"world_nether"}],"player_uuid":"4fefb418-f03c-46f2-bb0e-7a8e2d1c00ee","most_used_world":"NordicEraI (84.28%)","first_session":false,"mob_kills":13,"player_url_name":"Robberdrup","afk_time":"5m 14s","name":"Survival","player_kills":[],"end":"Jul 13 2021, 22:28","player_name":"Robberdrup","world_series":[{"name":"NordicEraI","y":4170854,"color":"#0099C6","drilldown":"NordicEraI"},{"name":"world_nether","y":777932,"color":"#66AA00","drilldown":"world_nether"}],"server_url_name":"Survival","server_uuid":"89eae527-4566-404d-a8f5-88200718a4d7","deaths":1},{"server_name":"Survival","start":"Jul 13 2021, 19:07","length":"1h 58m 11s","gm_series":[{"data":[["SURVIVAL",5751356],["SPECTATOR",0],["CREATIVE",0],["ADVENTURE",0]],"name":"NordicEraI","id":"NordicEraI"},{"data":[["SURVIVAL",257670],["SPECTATOR",0],["CREATIVE",0],["ADVENTURE",0]],"name":"world_nether","id":"world_nether"},{"data":[["SURVIVAL",1082129],["SPECTATOR",0],["CREATIVE",0],["ADVENTURE",0]],"name":"Resource","id":"Resource"}],"player_uuid":"4fefb418-f03c-46f2-bb0e-7a8e2d1c00ee","most_used_world":"NordicEraI (81.11%)","first_session":false,"mob_kills":21,"player_url_name":"Robberdrup","afk_time":"51m 12s","name":"Survival","player_kills":[],"end":"Jul 13 2021, 21:05","player_name":"Robberdrup","world_series":[{"name":"NordicEraI","y":5751356,"color":"#0099C6","drilldown":"NordicEraI"},{"name":"Resource","y":1082129,"color":"#66AA00","drilldown":"Resource"},{"name":"world_nether","y":257670,"color":"#316395","drilldown":"world_nether"}],"server_url_name":"Survival","server_uuid":"89eae527-4566-404d-a8f5-88200718a4d7","deaths":0},{"server_name":"Survival","start":"Jul 13 2021, 16:20","length":"1h 36s","gm_series":[{"data":[["SURVIVAL",1850057],["SPECTATOR",0],["CREATIVE",0],["ADVENTURE",0]],"name":"NordicEraI","id":"NordicEraI"},{"data":[["SURVIVAL",1786687],["SPECTATOR",0],["CREATIVE",0],["ADVENTURE",0]],"name":"Resource","id":"Resource"}],"player_uuid":"4fefb418-f03c-46f2-bb0e-7a8e2d1c00ee","most_used_world":"NordicEraI (50.87%)","first_session":false,"mob_kills":26,"player_url_name":"Robberdrup","afk_time":"0s","name":"Survival","player_kills":[],"end":"Jul 13 2021, 17:20","player_name":"Robberdrup","world_series":[{"name":"NordicEraI","y":1850057,"color":"#0099C6","drilldown":"NordicEraI"},{"name":"Resource","y":1786687,"color":"#66AA00","drilldown":"Resource"}],"server_url_name":"Survival","server_uuid":"89eae527-4566-404d-a8f5-88200718a4d7","deaths":0},{"server_name":"Survival","start":"Jul 13 2021, 11:21","length":"7m 55s","gm_series":[{"data":[["SURVIVAL",475267],["SPECTATOR",0],["CREATIVE",0],["ADVENTURE",0]],"name":"NordicEraI","id":"NordicEraI"}],"player_uuid":"4fefb418-f03c-46f2-bb0e-7a8e2d1c00ee","most_used_world":"NordicEraI (100%)","first_session":false,"mob_kills":1,"player_url_name":"Robberdrup","afk_time":"0s","name":"Survival","player_kills":[],"end":"Jul 13 2021, 11:29","player_name":"Robberdrup","world_series":[{"name":"NordicEraI","y":475267,"color":"#0099C6","drilldown":"NordicEraI"}],"server_url_name":"Survival","server_uuid":"89eae527-4566-404d-a8f5-88200718a4d7","deaths":0},{"server_name":"Survival","start":"Jul 12 2021, 21:38","length":"1h 32m 37s","gm_series":[{"data":[["SURVIVAL",4259524],["SPECTATOR",0],["CREATIVE",0],["ADVENTURE",0]],"name":"NordicEraI","id":"NordicEraI"},{"data":[["SURVIVAL",1298280],["SPECTATOR",0],["CREATIVE",0],["ADVENTURE",0]],"name":"Resource","id":"Resource"}],"player_uuid":"4fefb418-f03c-46f2-bb0e-7a8e2d1c00ee","most_used_world":"NordicEraI (76.64%)","first_session":false,"mob_kills":13,"player_url_name":"Robberdrup","afk_time":"0s","name":"Survival","player_kills":[],"end":"Jul 12 2021, 23:10","player_name":"Robberdrup","world_series":[{"name":"NordicEraI","y":4259524,"color":"#0099C6","drilldown":"NordicEraI"},{"name":"Resource","y":1298280,"color":"#66AA00","drilldown":"Resource"}],"server_url_name":"Survival","server_uuid":"89eae527-4566-404d-a8f5-88200718a4d7","deaths":0},{"server_name":"Survival","start":"Jul 12 2021, 20:56","length":"26m 38s","gm_series":[{"data":[["SURVIVAL",1598580],["SPECTATOR",0],["CREATIVE",0],["ADVENTURE",0]],"name":"NordicEraI","id":"NordicEraI"}],"player_uuid":"4fefb418-f03c-46f2-bb0e-7a8e2d1c00ee","most_used_world":"NordicEraI (100%)","first_session":false,"mob_kills":7,"player_url_name":"Robberdrup","afk_time":"0s","name":"Survival","player_kills":[],"end":"Jul 12 2021, 21:23","player_name":"Robberdrup","world_series":[{"name":"NordicEraI","y":1598580,"color":"#0099C6","drilldown":"NordicEraI"}],"server_url_name":"Survival","server_uuid":"89eae527-4566-404d-a8f5-88200718a4d7","deaths":0},{"server_name":"Survival","start":"Jul 12 2021, 15:58","length":"30m 36s","gm_series":[{"data":[["SURVIVAL",1836811],["SPECTATOR",0],["CREATIVE",0],["ADVENTURE",0]],"name":"NordicEraI","id":"NordicEraI"}],"player_uuid":"4fefb418-f03c-46f2-bb0e-7a8e2d1c00ee","most_used_world":"NordicEraI (100%)","first_session":false,"mob_kills":23,"player_url_name":"Robberdrup","afk_time":"0s","name":"Survival","player_kills":[],"end":"Jul 12 2021, 16:29","player_name":"Robberdrup","world_series":[{"name":"NordicEraI","y":1836811,"color":"#0099C6","drilldown":"NordicEraI"}],"server_url_name":"Survival","server_uuid":"89eae527-4566-404d-a8f5-88200718a4d7","deaths":0},{"server_name":"Survival","start":"Jul 12 2021, 11:45","length":"1h 43m 3s","gm_series":[{"data":[["SURVIVAL",6183941],["SPECTATOR",0],["CREATIVE",0],["ADVENTURE",0]],"name":"NordicEraI","id":"NordicEraI"}],"player_uuid":"4fefb418-f03c-46f2-bb0e-7a8e2d1c00ee","most_used_world":"NordicEraI (100%)","first_session":false,"mob_kills":30,"player_url_name":"Robberdrup","afk_time":"1h 5m 8s","name":"Survival","player_kills":[],"end":"Jul 12 2021, 13:28","player_name":"Robberdrup","world_series":[{"name":"NordicEraI","y":6183941,"color":"#0099C6","drilldown":"NordicEraI"}],"server_url_name":"Survival","server_uuid":"89eae527-4566-404d-a8f5-88200718a4d7","deaths":0},{"server_name":"Survival","start":"Jul 11 2021, 22:49","length":"3h 40m 45s","gm_series":[{"data":[["SURVIVAL",13245728],["SPECTATOR",0],["CREATIVE",0],["ADVENTURE",0]],"name":"NordicEraI","id":"NordicEraI"}],"player_uuid":"4fefb418-f03c-46f2-bb0e-7a8e2d1c00ee","most_used_world":"NordicEraI (100%)","first_session":false,"mob_kills":100,"player_url_name":"Robberdrup","afk_time":"0s","name":"Survival","player_kills":[],"end":"Jul 12 2021, 02:29","player_name":"Robberdrup","world_series":[{"name":"NordicEraI","y":13245728,"color":"#0099C6","drilldown":"NordicEraI"}],"server_url_name":"Survival","server_uuid":"89eae527-4566-404d-a8f5-88200718a4d7","deaths":0},{"server_name":"Survival","start":"Jul 11 2021, 22:43","length":"5m 23s","gm_series":[{"data":[["SURVIVAL",323468],["SPECTATOR",0],["CREATIVE",0],["ADVENTURE",0]],"name":"NordicEraI","id":"NordicEraI"}],"player_uuid":"4fefb418-f03c-46f2-bb0e-7a8e2d1c00ee","most_used_world":"NordicEraI (100%)","first_session":false,"mob_kills":0,"player_url_name":"Robberdrup","afk_time":"0s","name":"Survival","player_kills":[],"end":"Jul 11 2021, 22:48","player_name":"Robberdrup","world_series":[{"name":"NordicEraI","y":323468,"color":"#0099C6","drilldown":"NordicEraI"}],"server_url_name":"Survival","server_uuid":"89eae527-4566-404d-a8f5-88200718a4d7","deaths":0},{"server_name":"Survival","start":"Jul 11 2021, 22:42","length":"0s","gm_series":[{"data":[["SURVIVAL",147],["SPECTATOR",0],["CREATIVE",0],["ADVENTURE",0]],"name":"NordicEraI","id":"NordicEraI"}],"player_uuid":"4fefb418-f03c-46f2-bb0e-7a8e2d1c00ee","most_used_world":"NordicEraI (100%)","first_session":false,"mob_kills":0,"player_url_name":"Robberdrup","afk_time":"0s","name":"Survival","player_kills":[],"end":"Jul 11 2021, 22:42","player_name":"Robberdrup","world_series":[{"name":"NordicEraI","y":147,"color":"#0099C6","drilldown":"NordicEraI"}],"server_url_name":"Survival","server_uuid":"89eae527-4566-404d-a8f5-88200718a4d7","deaths":0},{"server_name":"Survival","start":"Jul 11 2021, 00:10","length":"1h 6m 50s","gm_series":[{"data":[["SURVIVAL",3869859],["SPECTATOR",0],["CREATIVE",0],["ADVENTURE",0]],"name":"NordicEraI","id":"NordicEraI"},{"data":[["SURVIVAL",141038],["SPECTATOR",0],["CREATIVE",0],["ADVENTURE",0]],"name":"world_nether","id":"world_nether"}],"player_uuid":"4fefb418-f03c-46f2-bb0e-7a8e2d1c00ee","most_used_world":"NordicEraI (96.48%)","first_session":false,"mob_kills":45,"player_url_name":"Robberdrup","afk_time":"0s","name":"Survival","player_kills":[],"end":"Jul 11 2021, 01:17","player_name":"Robberdrup","world_series":[{"name":"NordicEraI","y":3869859,"color":"#0099C6","drilldown":"NordicEraI"},{"name":"world_nether","y":141038,"color":"#66AA00","drilldown":"world_nether"}],"server_url_name":"Survival","server_uuid":"89eae527-4566-404d-a8f5-88200718a4d7","deaths":1},{"server_name":"Survival","start":"Jul 10 2021, 20:17","length":"1h 37m 3s","gm_series":[{"data":[["SURVIVAL",5823157],["SPECTATOR",0],["CREATIVE",0],["ADVENTURE",0]],"name":"NordicEraI","id":"NordicEraI"}],"player_uuid":"4fefb418-f03c-46f2-bb0e-7a8e2d1c00ee","most_used_world":"NordicEraI (100%)","first_session":false,"mob_kills":67,"player_url_name":"Robberdrup","afk_time":"0s","name":"Survival","player_kills":[],"end":"Jul 10 2021, 21:54","player_name":"Robberdrup","world_series":[{"name":"NordicEraI","y":5823157,"color":"#0099C6","drilldown":"NordicEraI"}],"server_url_name":"Survival","server_uuid":"89eae527-4566-404d-a8f5-88200718a4d7","deaths":0},{"server_name":"Survival","start":"Jul 10 2021, 18:51","length":"38m 23s","gm_series":[{"data":[["SURVIVAL",2303080],["SPECTATOR",0],["CREATIVE",0],["ADVENTURE",0]],"name":"NordicEraI","id":"NordicEraI"}],"player_uuid":"4fefb418-f03c-46f2-bb0e-7a8e2d1c00ee","most_used_world":"NordicEraI (100%)","first_session":false,"mob_kills":22,"player_url_name":"Robberdrup","afk_time":"0s","name":"Survival","player_kills":[],"end":"Jul 10 2021, 19:29","player_name":"Robberdrup","world_series":[{"name":"NordicEraI","y":2303080,"color":"#0099C6","drilldown":"NordicEraI"}],"server_url_name":"Survival","server_uuid":"89eae527-4566-404d-a8f5-88200718a4d7","deaths":0},{"server_name":"Survival","start":"Jul 10 2021, 15:45","length":"20m 45s","gm_series":[{"data":[["SURVIVAL",1245815],["SPECTATOR",0],["CREATIVE",0],["ADVENTURE",0]],"name":"NordicEraI","id":"NordicEraI"}],"player_uuid":"4fefb418-f03c-46f2-bb0e-7a8e2d1c00ee","most_used_world":"NordicEraI (100%)","first_session":false,"mob_kills":10,"player_url_name":"Robberdrup","afk_time":"0s","name":"Survival","player_kills":[],"end":"Jul 10 2021, 16:06","player_name":"Robberdrup","world_series":[{"name":"NordicEraI","y":1245815,"color":"#0099C6","drilldown":"NordicEraI"}],"server_url_name":"Survival","server_uuid":"89eae527-4566-404d-a8f5-88200718a4d7","deaths":0},{"server_name":"Survival","start":"Jul 10 2021, 14:36","length":"35m 59s","gm_series":[{"data":[["SURVIVAL",2159719],["SPECTATOR",0],["CREATIVE",0],["ADVENTURE",0]],"name":"NordicEraI","id":"NordicEraI"}],"player_uuid":"4fefb418-f03c-46f2-bb0e-7a8e2d1c00ee","most_used_world":"NordicEraI (100%)","first_session":false,"mob_kills":31,"player_url_name":"Robberdrup","afk_time":"0s","name":"Survival","player_kills":[],"end":"Jul 10 2021, 15:12","player_name":"Robberdrup","world_series":[{"name":"NordicEraI","y":2159719,"color":"#0099C6","drilldown":"NordicEraI"}],"server_url_name":"Survival","server_uuid":"89eae527-4566-404d-a8f5-88200718a4d7","deaths":0},{"server_name":"Survival","start":"Jul 9 2021, 14:22","length":"57m 9s","gm_series":[{"data":[["SURVIVAL",3429843],["SPECTATOR",0],["CREATIVE",0],["ADVENTURE",0]],"name":"NordicEraI","id":"NordicEraI"}],"player_uuid":"4fefb418-f03c-46f2-bb0e-7a8e2d1c00ee","most_used_world":"NordicEraI (100%)","first_session":false,"mob_kills":43,"player_url_name":"Robberdrup","afk_time":"0s","name":"Survival","player_kills":[],"end":"Jul 9 2021, 15:19","player_name":"Robberdrup","world_series":[{"name":"NordicEraI","y":3429843,"color":"#0099C6","drilldown":"NordicEraI"}],"server_url_name":"Survival","server_uuid":"89eae527-4566-404d-a8f5-88200718a4d7","deaths":0},{"server_name":"Survival","start":"Jul 9 2021, 12:23","length":"42m 32s","gm_series":[{"data":[["SURVIVAL",2552550],["SPECTATOR",0],["CREATIVE",0],["ADVENTURE",0]],"name":"NordicEraI","id":"NordicEraI"}],"player_uuid":"4fefb418-f03c-46f2-bb0e-7a8e2d1c00ee","most_used_world":"NordicEraI (100%)","first_session":false,"mob_kills":38,"player_url_name":"Robberdrup","afk_time":"0s","name":"Survival","player_kills":[],"end":"Jul 9 2021, 13:06","player_name":"Robberdrup","world_series":[{"name":"NordicEraI","y":2552550,"color":"#0099C6","drilldown":"NordicEraI"}],"server_url_name":"Survival","server_uuid":"89eae527-4566-404d-a8f5-88200718a4d7","deaths":0},{"server_name":"Survival","start":"Jul 8 2021, 21:29","length":"1h 35m 15s","gm_series":[{"data":[["SURVIVAL",5715488],["SPECTATOR",0],["CREATIVE",0],["ADVENTURE",0]],"name":"NordicEraI","id":"NordicEraI"}],"player_uuid":"4fefb418-f03c-46f2-bb0e-7a8e2d1c00ee","most_used_world":"NordicEraI (100%)","first_session":false,"mob_kills":50,"player_url_name":"Robberdrup","afk_time":"0s","name":"Survival","player_kills":[],"end":"Jul 8 2021, 23:04","player_name":"Robberdrup","world_series":[{"name":"NordicEraI","y":5715488,"color":"#0099C6","drilldown":"NordicEraI"}],"server_url_name":"Survival","server_uuid":"89eae527-4566-404d-a8f5-88200718a4d7","deaths":1},{"server_name":"Survival","start":"Jul 8 2021, 19:28","length":"11m 56s","gm_series":[{"data":[["SURVIVAL",716507],["SPECTATOR",0],["CREATIVE",0],["ADVENTURE",0]],"name":"NordicEraI","id":"NordicEraI"}],"player_uuid":"4fefb418-f03c-46f2-bb0e-7a8e2d1c00ee","most_used_world":"NordicEraI (100%)","first_session":false,"mob_kills":5,"player_url_name":"Robberdrup","afk_time":"0s","name":"Survival","player_kills":[],"end":"Jul 8 2021, 19:40","player_name":"Robberdrup","world_series":[{"name":"NordicEraI","y":716507,"color":"#0099C6","drilldown":"NordicEraI"}],"server_url_name":"Survival","server_uuid":"89eae527-4566-404d-a8f5-88200718a4d7","deaths":0},{"server_name":"Survival","start":"Jul 8 2021, 17:42","length":"4s","gm_series":[{"data":[["SURVIVAL",4926],["SPECTATOR",0],["CREATIVE",0],["ADVENTURE",0]],"name":"NordicEraI","id":"NordicEraI"}],"player_uuid":"4fefb418-f03c-46f2-bb0e-7a8e2d1c00ee","most_used_world":"NordicEraI (100%)","first_session":false,"mob_kills":0,"player_url_name":"Robberdrup","afk_time":"0s","name":"Survival","player_kills":[],"end":"Jul 8 2021, 17:42","player_name":"Robberdrup","world_series":[{"name":"NordicEraI","y":4926,"color":"#0099C6","drilldown":"NordicEraI"}],"server_url_name":"Survival","server_uuid":"89eae527-4566-404d-a8f5-88200718a4d7","deaths":0},{"server_name":"Survival","start":"Jul 8 2021, 13:37","length":"1h 31m 13s","gm_series":[{"data":[["SURVIVAL",5473906],["SPECTATOR",0],["CREATIVE",0],["ADVENTURE",0]],"name":"NordicEraI","id":"NordicEraI"}],"player_uuid":"4fefb418-f03c-46f2-bb0e-7a8e2d1c00ee","most_used_world":"NordicEraI (100%)","first_session":false,"mob_kills":76,"player_url_name":"Robberdrup","afk_time":"0s","name":"Survival","player_kills":[],"end":"Jul 8 2021, 15:08","player_name":"Robberdrup","world_series":[{"name":"NordicEraI","y":5473906,"color":"#0099C6","drilldown":"NordicEraI"}],"server_url_name":"Survival","server_uuid":"89eae527-4566-404d-a8f5-88200718a4d7","deaths":1},{"server_name":"Survival","start":"Jul 8 2021, 12:27","length":"11m 22s","gm_series":[{"data":[["SURVIVAL",682191],["SPECTATOR",0],["CREATIVE",0],["ADVENTURE",0]],"name":"NordicEraI","id":"NordicEraI"}],"player_uuid":"4fefb418-f03c-46f2-bb0e-7a8e2d1c00ee","most_used_world":"NordicEraI (100%)","first_session":true,"mob_kills":10,"player_url_name":"Robberdrup","afk_time":"0s","name":"Survival","player_kills":[],"end":"Jul 8 2021, 12:38","player_name":"Robberdrup","world_series":[{"name":"NordicEraI","y":682191,"color":"#0099C6","drilldown":"NordicEraI"}],"server_url_name":"Survival","server_uuid":"89eae527-4566-404d-a8f5-88200718a4d7","deaths":0}],"calendar_series":[{"title":"Registered: Jul 8 2021, 12:27","start":1625740056323,"color":"#8BC34A"},{"title":"Playtime: 3h 12m 11s","start":"2021-07-10","color":"#4CAF50"},{"title":"Sessions: 4","start":"2021-07-10"},{"title":"Playtime: 4h 12m 57s","start":"2021-07-12","color":"#4CAF50"},{"title":"Sessions: 4","start":"2021-07-12"},{"title":"Playtime: 4h 53m ","start":"2021-07-11","color":"#4CAF50"},{"title":"Sessions: 4","start":"2021-07-11"},{"title":"Playtime: 5h 1m 39s","start":"2021-07-14","color":"#4CAF50"},{"title":"Sessions: 7","start":"2021-07-14"},{"title":"Playtime: 4h 29m 11s","start":"2021-07-13","color":"#4CAF50"},{"title":"Sessions: 4","start":"2021-07-13"},{"title":"Playtime: 2h 38m 32s","start":"2021-07-16","color":"#4CAF50"},{"title":"Sessions: 3","start":"2021-07-16"},{"title":"Playtime: 1h 18m 29s","start":"2021-07-15","color":"#4CAF50"},{"title":"Sessions: 1","start":"2021-07-15"},{"title":"Playtime: 11m 26s","start":"2021-07-26","color":"#4CAF50"},{"title":"Sessions: 1","start":"2021-07-26"},{"title":"Playtime: 1h 39m 42s","start":"2021-07-09","color":"#4CAF50"},{"title":"Sessions: 2","start":"2021-07-09"},{"title":"Playtime: 3h 29m 53s","start":"2021-07-08","color":"#4CAF50"},{"title":"Sessions: 5","start":"2021-07-08"},{"title":"Session: 11m 26s","start":1627327844869,"end":1627328530967},{"title":"Session: 38m 36s","start":1626473297782,"end":1626475614110},{"title":"Session: 39m 59s","start":1626457771005,"end":1626460170079},{"title":"Session: 1h 19m 57s","start":1626441602106,"end":1626446399538},{"title":"Session: 1h 18m 29s","start":1626388838638,"end":1626393548027},{"title":"Session: 2h 5m 44s","start":1626298680028,"end":1626306224712},{"title":"Session: 5m 50s","start":1626298329004,"end":1626298679600},{"title":"Session: 1h 22s","start":1626294706157,"end":1626298328726},{"title":"Session: 12m 11s","start":1626293974418,"end":1626294705907},{"title":"Session: 10m 1s","start":1626276249605,"end":1626276851181},{"title":"Session: 40m 8s","start":1626261236468,"end":1626263645410},{"title":"Session: 47m 19s","start":1626256164562,"end":1626259004410},{"title":"Session: 1h 22m 28s","start":1626210372847,"end":1626215321631},{"title":"Session: 1h 58m 11s","start":1626203236691,"end":1626210327846},{"title":"Session: 1h 36s","start":1626193213234,"end":1626196849978},{"title":"Session: 7m 55s","start":1626175281533,"end":1626175756800},{"title":"Session: 1h 32m 37s","start":1626125893260,"end":1626131451064},{"title":"Session: 26m 38s","start":1626123382066,"end":1626124980646},{"title":"Session: 30m 36s","start":1626105511870,"end":1626107348681},{"title":"Session: 1h 43m 3s","start":1626090353101,"end":1626096537042},{"title":"Session: 3h 40m 45s","start":1626043748233,"end":1626056993961},{"title":"Session: 5m 23s","start":1626043393975,"end":1626043717443},{"title":"Session: 0s","start":1626043333411,"end":1626043333558},{"title":"Session: 1h 6m 50s","start":1625962247406,"end":1625966258301},{"title":"Session: 1h 37m 3s","start":1625948261845,"end":1625954085002},{"title":"Session: 38m 23s","start":1625943064855,"end":1625945367935},{"title":"Session: 20m 45s","start":1625931948640,"end":1625933194455},{"title":"Session: 35m 59s","start":1625927765230,"end":1625929924949},{"title":"Session: 57m 9s","start":1625840563637,"end":1625843993480},{"title":"Session: 42m 32s","start":1625833409316,"end":1625835961866},{"title":"Session: 1h 35m 15s","start":1625779746550,"end":1625785462038},{"title":"Session: 11m 56s","start":1625772499422,"end":1625773215929},{"title":"Session: 4s","start":1625766122732,"end":1625766127658},{"title":"Session: 1h 31m 13s","start":1625751446877,"end":1625756920783},{"title":"Session: 11m 22s","start":1625747256586,"end":1625747938777}],"player_deaths":[],"gm_series":[{"data":[["SURVIVAL",104370647],["SPECTATOR",0],["CREATIVE",0],["ADVENTURE",0]],"name":"NordicEraI","id":"NordicEraI"},{"data":[["SURVIVAL",3486798],["SPECTATOR",0],["CREATIVE",0],["ADVENTURE",0]],"name":"world_nether","id":"world_nether"},{"data":[["SURVIVAL",4167096],["SPECTATOR",0],["CREATIVE",0],["ADVENTURE",0]],"name":"Resource","id":"Resource"}],"world_pie_series":[{"name":"NordicEraI","y":104370647,"color":"#0099C6","drilldown":"NordicEraI"},{"name":"Resource","y":4167096,"color":"#66AA00","drilldown":"Resource"},{"name":"world_nether","y":3486798,"color":"#316395","drilldown":"world_nether"}],"server_pie_colors":["#0099C6","#66AA00","#316395","#994499","#22AA99","#AAAA11","#6633CC","#E67300","#329262","#5574A6"],"servers":[{"server_name":"Survival","last_seen":"Jul 26 2021, 19:42","registered":"Jul 8 2021, 12:27","gm_series":[{"data":[["SURVIVAL",104370647],["SPECTATOR",0],["CREATIVE",0],["ADVENTURE",0]],"name":"NordicEraI","id":"NordicEraI"},{"data":[["SURVIVAL",3486798],["SPECTATOR",0],["CREATIVE",0],["ADVENTURE",0]],"name":"world_nether","id":"world_nether"},{"data":[["SURVIVAL",4167096],["SPECTATOR",0],["CREATIVE",0],["ADVENTURE",0]],"name":"Resource","id":"Resource"}],"playtime":"1d 7h 7m 4s","session_median":"40m 8s","world_pie_series":[{"name":"NordicEraI","y":104370647,"color":"#0099C6","drilldown":"NordicEraI"},{"name":"Resource","y":4167096,"color":"#66AA00","drilldown":"Resource"},{"name":"world_nether","y":3486798,"color":"#316395","drilldown":"world_nether"}],"operator":false,"mob_kills":803,"afk_time":"2h 8m 29s","session_count":35,"player_kills":0,"longest_session_length":"3h 40m 45s","banned":false,"deaths":7}],"server_pie_series":[{"name":"Survival","y":112024541}],"online_activity":{"session_count_30d":0,"session_count_7d":0,"afk_time_7d":"0s","mob_kill_count_30d":0,"active_playtime_7d":"0s","mob_kill_count_7d":0,"afk_time_30d":"0s","average_session_length_30d":"0s","death_count_30d":0,"active_playtime_30d":"0s","average_session_length_7d":"0s","median_session_length_7d":"-","median_session_length_30d":"-","playtime_30d":"0s","player_kill_count_30d":0,"death_count_7d":0,"playtime_7d":"0s","player_kill_count_7d":0},"player_kills":[],"sessions_per_page":50,"punchcard_series":[{"x":0,"y":0,"z":0,"marker":{"radius":0}},{"x":3600000,"y":0,"z":0,"marker":{"radius":0}},{"x":7200000,"y":0,"z":0,"marker":{"radius":0}},{"x":10800000,"y":0,"z":0,"marker":{"radius":0}},{"x":14400000,"y":0,"z":0,"marker":{"radius":0}},{"x":18000000,"y":0,"z":0,"marker":{"radius":0}},{"x":21600000,"y":0,"z":0,"marker":{"radius":0}},{"x":25200000,"y":0,"z":0,"marker":{"radius":0}},{"x":28800000,"y":0,"z":0,"marker":{"radius":0}},{"x":32400000,"y":0,"z":0,"marker":{"radius":0}},{"x":36000000,"y":0,"z":0,"marker":{"radius":0}},{"x":39600000,"y":0,"z":7,"marker":{"radius":7}},{"x":43200000,"y":0,"z":0,"marker":{"radius":0}},{"x":46800000,"y":0,"z":0,"marker":{"radius":0}},{"x":50400000,"y":0,"z":0,"marker":{"radius":0}},{"x":54000000,"y":0,"z":7,"marker":{"radius":7}},{"x":57600000,"y":0,"z":0,"marker":{"radius":0}},{"x":61200000,"y":0,"z":0,"marker":{"radius":0}},{"x":64800000,"y":0,"z":0,"marker":{"radius":0}},{"x":68400000,"y":0,"z":7,"marker":{"radius":7}},{"x":72000000,"y":0,"z":7,"marker":{"radius":7}},{"x":75600000,"y":0,"z":7,"marker":{"radius":7}},{"x":79200000,"y":0,"z":0,"marker":{"radius":0}},{"x":82800000,"y":0,"z":0,"marker":{"radius":0}},{"x":0,"y":1,"z":0,"marker":{"radius":0}},{"x":3600000,"y":1,"z":0,"marker":{"radius":0}},{"x":7200000,"y":1,"z":0,"marker":{"radius":0}},{"x":10800000,"y":1,"z":0,"marker":{"radius":0}},{"x":14400000,"y":1,"z":0,"marker":{"radius":0}},{"x":18000000,"y":1,"z":0,"marker":{"radius":0}},{"x":21600000,"y":1,"z":0,"marker":{"radius":0}},{"x":25200000,"y":1,"z":0,"marker":{"radius":0}},{"x":28800000,"y":1,"z":0,"marker":{"radius":0}},{"x":32400000,"y":1,"z":0,"marker":{"radius":0}},{"x":36000000,"y":1,"z":0,"marker":{"radius":0}},{"x":39600000,"y":1,"z":7,"marker":{"radius":7}},{"x":43200000,"y":1,"z":0,"marker":{"radius":0}},{"x":46800000,"y":1,"z":0,"marker":{"radius":0}},{"x":50400000,"y":1,"z":0,"marker":{"radius":0}},{"x":54000000,"y":1,"z":0,"marker":{"radius":0}},{"x":57600000,"y":1,"z":7,"marker":{"radius":7}},{"x":61200000,"y":1,"z":0,"marker":{"radius":0}},{"x":64800000,"y":1,"z":0,"marker":{"radius":0}},{"x":68400000,"y":1,"z":7,"marker":{"radius":7}},{"x":72000000,"y":1,"z":0,"marker":{"radius":0}},{"x":75600000,"y":1,"z":7,"marker":{"radius":7}},{"x":79200000,"y":1,"z":0,"marker":{"radius":0}},{"x":82800000,"y":1,"z":0,"marker":{"radius":0}},{"x":0,"y":2,"z":0,"marker":{"radius":0}},{"x":3600000,"y":2,"z":0,"marker":{"radius":0}},{"x":7200000,"y":2,"z":0,"marker":{"radius":0}},{"x":10800000,"y":2,"z":0,"marker":{"radius":0}},{"x":14400000,"y":2,"z":0,"marker":{"radius":0}},{"x":18000000,"y":2,"z":0,"marker":{"radius":0}},{"x":21600000,"y":2,"z":0,"marker":{"radius":0}},{"x":25200000,"y":2,"z":0,"marker":{"radius":0}},{"x":28800000,"y":2,"z":0,"marker":{"radius":0}},{"x":32400000,"y":2,"z":7,"marker":{"radius":7}},{"x":36000000,"y":2,"z":0,"marker":{"radius":0}},{"x":39600000,"y":2,"z":7,"marker":{"radius":7}},{"x":43200000,"y":2,"z":0,"marker":{"radius":0}},{"x":46800000,"y":2,"z":0,"marker":{"radius":0}},{"x":50400000,"y":2,"z":0,"marker":{"radius":0}},{"x":54000000,"y":2,"z":7,"marker":{"radius":7}},{"x":57600000,"y":2,"z":0,"marker":{"radius":0}},{"x":61200000,"y":2,"z":0,"marker":{"radius":0}},{"x":64800000,"y":2,"z":0,"marker":{"radius":0}},{"x":68400000,"y":2,"z":0,"marker":{"radius":0}},{"x":72000000,"y":2,"z":10,"marker":{"radius":10}},{"x":75600000,"y":2,"z":10,"marker":{"radius":10}},{"x":79200000,"y":2,"z":0,"marker":{"radius":0}},{"x":82800000,"y":2,"z":0,"marker":{"radius":0}},{"x":0,"y":3,"z":0,"marker":{"radius":0}},{"x":3600000,"y":3,"z":0,"marker":{"radius":0}},{"x":7200000,"y":3,"z":0,"marker":{"radius":0}},{"x":10800000,"y":3,"z":0,"marker":{"radius":0}},{"x":14400000,"y":3,"z":0,"marker":{"radius":0}},{"x":18000000,"y":3,"z":0,"marker":{"radius":0}},{"x":21600000,"y":3,"z":0,"marker":{"radius":0}},{"x":25200000,"y":3,"z":0,"marker":{"radius":0}},{"x":28800000,"y":3,"z":0,"marker":{"radius":0}},{"x":32400000,"y":3,"z":0,"marker":{"radius":0}},{"x":36000000,"y":3,"z":0,"marker":{"radius":0}},{"x":39600000,"y":3,"z":0,"marker":{"radius":0}},{"x":43200000,"y":3,"z":7,"marker":{"radius":7}},{"x":46800000,"y":3,"z":7,"marker":{"radius":7}},{"x":50400000,"y":3,"z":0,"marker":{"radius":0}},{"x":54000000,"y":3,"z":0,"marker":{"radius":0}},{"x":57600000,"y":3,"z":0,"marker":{"radius":0}},{"x":61200000,"y":3,"z":7,"marker":{"radius":7}},{"x":64800000,"y":3,"z":0,"marker":{"radius":0}},{"x":68400000,"y":3,"z":7,"marker":{"radius":7}},{"x":72000000,"y":3,"z":0,"marker":{"radius":0}},{"x":75600000,"y":3,"z":7,"marker":{"radius":7}},{"x":79200000,"y":3,"z":7,"marker":{"radius":7}},{"x":82800000,"y":3,"z":0,"marker":{"radius":0}},{"x":0,"y":4,"z":0,"marker":{"radius":0}},{"x":3600000,"y":4,"z":0,"marker":{"radius":0}},{"x":7200000,"y":4,"z":0,"marker":{"radius":0}},{"x":10800000,"y":4,"z":0,"marker":{"radius":0}},{"x":14400000,"y":4,"z":0,"marker":{"radius":0}},{"x":18000000,"y":4,"z":0,"marker":{"radius":0}},{"x":21600000,"y":4,"z":0,"marker":{"radius":0}},{"x":25200000,"y":4,"z":0,"marker":{"radius":0}},{"x":28800000,"y":4,"z":0,"marker":{"radius":0}},{"x":32400000,"y":4,"z":0,"marker":{"radius":0}},{"x":36000000,"y":4,"z":0,"marker":{"radius":0}},{"x":39600000,"y":4,"z":0,"marker":{"radius":0}},{"x":43200000,"y":4,"z":7,"marker":{"radius":7}},{"x":46800000,"y":4,"z":7,"marker":{"radius":7}},{"x":50400000,"y":4,"z":7,"marker":{"radius":7}},{"x":54000000,"y":4,"z":0,"marker":{"radius":0}},{"x":57600000,"y":4,"z":0,"marker":{"radius":0}},{"x":61200000,"y":4,"z":7,"marker":{"radius":7}},{"x":64800000,"y":4,"z":0,"marker":{"radius":0}},{"x":68400000,"y":4,"z":0,"marker":{"radius":0}},{"x":72000000,"y":4,"z":0,"marker":{"radius":0}},{"x":75600000,"y":4,"z":0,"marker":{"radius":0}},{"x":79200000,"y":4,"z":7,"marker":{"radius":7}},{"x":82800000,"y":4,"z":0,"marker":{"radius":0}},{"x":0,"y":5,"z":0,"marker":{"radius":0}},{"x":3600000,"y":5,"z":0,"marker":{"radius":0}},{"x":7200000,"y":5,"z":0,"marker":{"radius":0}},{"x":10800000,"y":5,"z":0,"marker":{"radius":0}},{"x":14400000,"y":5,"z":0,"marker":{"radius":0}},{"x":18000000,"y":5,"z":0,"marker":{"radius":0}},{"x":21600000,"y":5,"z":0,"marker":{"radius":0}},{"x":25200000,"y":5,"z":0,"marker":{"radius":0}},{"x":28800000,"y":5,"z":0,"marker":{"radius":0}},{"x":32400000,"y":5,"z":0,"marker":{"radius":0}},{"x":36000000,"y":5,"z":0,"marker":{"radius":0}},{"x":39600000,"y":5,"z":0,"marker":{"radius":0}},{"x":43200000,"y":5,"z":0,"marker":{"radius":0}},{"x":46800000,"y":5,"z":0,"marker":{"radius":0}},{"x":50400000,"y":5,"z":7,"marker":{"radius":7}},{"x":54000000,"y":5,"z":7,"marker":{"radius":7}},{"x":57600000,"y":5,"z":0,"marker":{"radius":0}},{"x":61200000,"y":5,"z":0,"marker":{"radius":0}},{"x":64800000,"y":5,"z":7,"marker":{"radius":7}},{"x":68400000,"y":5,"z":0,"marker":{"radius":0}},{"x":72000000,"y":5,"z":7,"marker":{"radius":7}},{"x":75600000,"y":5,"z":0,"marker":{"radius":0}},{"x":79200000,"y":5,"z":0,"marker":{"radius":0}},{"x":82800000,"y":5,"z":0,"marker":{"radius":0}},{"x":0,"y":6,"z":7,"marker":{"radius":7}},{"x":3600000,"y":6,"z":0,"marker":{"radius":0}},{"x":7200000,"y":6,"z":0,"marker":{"radius":0}},{"x":10800000,"y":6,"z":0,"marker":{"radius":0}},{"x":14400000,"y":6,"z":0,"marker":{"radius":0}},{"x":18000000,"y":6,"z":0,"marker":{"radius":0}},{"x":21600000,"y":6,"z":0,"marker":{"radius":0}},{"x":25200000,"y":6,"z":0,"marker":{"radius":0}},{"x":28800000,"y":6,"z":0,"marker":{"radius":0}},{"x":32400000,"y":6,"z":0,"marker":{"radius":0}},{"x":36000000,"y":6,"z":0,"marker":{"radius":0}},{"x":39600000,"y":6,"z":0,"marker":{"radius":0}},{"x":43200000,"y":6,"z":0,"marker":{"radius":0}},{"x":46800000,"y":6,"z":0,"marker":{"radius":0}},{"x":50400000,"y":6,"z":0,"marker":{"radius":0}},{"x":54000000,"y":6,"z":0,"marker":{"radius":0}},{"x":57600000,"y":6,"z":0,"marker":{"radius":0}},{"x":61200000,"y":6,"z":0,"marker":{"radius":0}},{"x":64800000,"y":6,"z":0,"marker":{"radius":0}},{"x":68400000,"y":6,"z":0,"marker":{"radius":0}},{"x":72000000,"y":6,"z":0,"marker":{"radius":0}},{"x":75600000,"y":6,"z":0,"marker":{"radius":0}},{"x":79200000,"y":6,"z":14,"marker":{"radius":14}},{"x":82800000,"y":6,"z":0,"marker":{"radius":0}}],"nicknames":[{"nickname":"Robberdrup","server":"Survival","date":"Jul 26 2021, 19:42"}],"connections":[{"geolocation":"Denmark","date":"Jul 26 2021, 19:30"}],"info":{"kick_count":5,"last_seen":"Jul 26 2021, 19:42","favorite_server":"Survival","mob_kill_count":803,"player_kill_count":0,"registered":"Jul 8 2021, 12:27","activity_index_group":"Inactive","playtime":"1d 7h 7m 4s","session_median":"40m 8s","active_playtime":"1d 4h 58m 34s","operator":false,"afk_time":"2h 8m 29s","death_count":7,"worst_ping":"Unavailable","session_count":35,"online":false,"longest_session_length":"3h 40m 45s","best_ping":"Unavailable","banned":false,"activity_index":"0","average_ping":"Unavailable"},"first_day":1}