{"kill_data":{"deaths_7d":14,"mob_deaths_7d":14,"mob_kills_total":6,"player_kdr_30d":"0","player_kills_7d":0,"player_deaths_total":0,"deaths_30d":14,"deaths_total":14,"player_kills_total":0,"mob_deaths_30d":14,"player_deaths_30d":0,"mob_kdr_30d":"0.43","player_kdr_total":"0","weapon_3rd":"-","mob_kdr_7d":"0.43","player_kdr_7d":"0","player_kills_30d":0,"weapon_2nd":"-","player_deaths_7d":0,"mob_deaths_total":14,"mob_kills_7d":6,"mob_kdr_total":"0.43","weapon_1st":"-","mob_kills_30d":6},"sessions":[{"server_name":"Survival","start":"Today, 01:37","length":"11m 24s","gm_series":[{"data":[["SURVIVAL",684325],["SPECTATOR",0],["CREATIVE",0],["ADVENTURE",0]],"name":"NordicII","id":"NordicII"}],"player_uuid":"8b2c6bd4-ac48-4181-9b20-b2f78d1f0c95","most_used_world":"NordicII (100%)","first_session":false,"mob_kills":0,"player_url_name":"toitstar","afk_time":"0s","name":"Survival","player_kills":[],"end":"Today, 01:48","player_name":"toitstar","world_series":[{"name":"NordicII","y":684325,"color":"#0099C6","drilldown":"NordicII"}],"avg_ping":"24.4 ms","server_url_name":"Survival","server_uuid":"89eae527-4566-404d-a8f5-88200718a4d7","deaths":0},{"server_name":"Survival","start":"Tuesday, 18:46","length":"49s","gm_series":[{"data":[["SURVIVAL",49551],["SPECTATOR",0],["CREATIVE",0],["ADVENTURE",0]],"name":"NordicII","id":"NordicII"}],"player_uuid":"8b2c6bd4-ac48-4181-9b20-b2f78d1f0c95","most_used_world":"NordicII (100%)","first_session":false,"mob_kills":0,"player_url_name":"toitstar","afk_time":"0s","name":"Survival","player_kills":[],"end":"Tuesday, 18:46","player_name":"toitstar","world_series":[{"name":"NordicII","y":49551,"color":"#0099C6","drilldown":"NordicII"}],"server_url_name":"Survival","server_uuid":"89eae527-4566-404d-a8f5-88200718a4d7","deaths":0},{"server_name":"Survival","start":"Tuesday, 18:35","length":"10m 17s","gm_series":[{"data":[["SURVIVAL",617131],["SPECTATOR",0],["CREATIVE",0],["ADVENTURE",0]],"name":"NordicII","id":"NordicII"}],"player_uuid":"8b2c6bd4-ac48-4181-9b20-b2f78d1f0c95","most_used_world":"NordicII (100%)","first_session":false,"mob_kills":0,"player_url_name":"toitstar","afk_time":"6m 9s","name":"Survival","player_kills":[],"end":"Tuesday, 18:46","player_name":"toitstar","world_series":[{"name":"NordicII","y":617131,"color":"#0099C6","drilldown":"NordicII"}],"avg_ping":"114.33 ms","server_url_name":"Survival","server_uuid":"89eae527-4566-404d-a8f5-88200718a4d7","deaths":0},{"server_name":"Survival","start":"Tuesday, 16:45","length":"1h 45m 48s","gm_series":[{"data":[["SURVIVAL",6348333],["SPECTATOR",0],["CREATIVE",0],["ADVENTURE",0]],"name":"NordicII","id":"NordicII"}],"player_uuid":"8b2c6bd4-ac48-4181-9b20-b2f78d1f0c95","most_used_world":"NordicII (100%)","first_session":false,"mob_kills":2,"player_url_name":"toitstar","afk_time":"3m 12s","name":"Survival","player_kills":[],"end":"Tuesday, 18:31","player_name":"toitstar","world_series":[{"name":"NordicII","y":6348333,"color":"#0099C6","drilldown":"NordicII"}],"avg_ping":"198.35 ms","server_url_name":"Survival","server_uuid":"89eae527-4566-404d-a8f5-88200718a4d7","deaths":14},{"server_name":"Survival","start":"Tuesday, 15:40","length":"30m 42s","gm_series":[{"data":[["SURVIVAL",1571],["SPECTATOR",0],["CREATIVE",0],["ADVENTURE",0]],"name":"NordicEraI","id":"NordicEraI"},{"data":[["SURVIVAL",1840756],["SPECTATOR",0],["CREATIVE",0],["ADVENTURE",0]],"name":"NordicII","id":"NordicII"}],"player_uuid":"8b2c6bd4-ac48-4181-9b20-b2f78d1f0c95","most_used_world":"NordicII (99.91%)","first_session":true,"mob_kills":4,"player_url_name":"toitstar","afk_time":"0s","name":"Survival","player_kills":[],"end":"Tuesday, 16:10","player_name":"toitstar","world_series":[{"name":"NordicEraI","y":1571,"color":"#0099C6","drilldown":"NordicEraI"},{"name":"NordicII","y":1840756,"color":"#66AA00","drilldown":"NordicII"}],"avg_ping":"89.12 ms","server_url_name":"Survival","server_uuid":"89eae527-4566-404d-a8f5-88200718a4d7","deaths":0}],"calendar_series":[{"title":"Registered: Tuesday, 15:40","start":1640702413376,"color":"#8BC34A"},{"title":"Playtime: 11m 24s","start":"2022-01-01","color":"#4CAF50"},{"title":"Sessions: 1","start":"2022-01-01"},{"title":"Playtime: 2h 27m 37s","start":"2021-12-28","color":"#4CAF50"},{"title":"Sessions: 4","start":"2021-12-28"},{"title":"Session: 11m 24s","start":1641001040753,"end":1641001725078},{"title":"Session: 49s","start":1640717164007,"end":1640717213558},{"title":"Session: 10m 17s","start":1640716543010,"end":1640717160141},{"title":"Session: 1h 45m 48s","start":1640709915402,"end":1640716263735},{"title":"Session: 30m 42s","start":1640706013486,"end":1640707855813}],"player_deaths":[],"gm_series":[{"data":[["SURVIVAL",1571],["SPECTATOR",0],["CREATIVE",0],["ADVENTURE",0]],"name":"NordicEraI","id":"NordicEraI"},{"data":[["SURVIVAL",9540096],["SPECTATOR",0],["CREATIVE",0],["ADVENTURE",0]],"name":"NordicII","id":"NordicII"}],"world_pie_series":[{"name":"NordicEraI","y":1571,"color":"#0099C6","drilldown":"NordicEraI"},{"name":"NordicII","y":9540096,"color":"#66AA00","drilldown":"NordicII"}],"server_pie_colors":["#0099C6","#66AA00","#316395","#994499","#22AA99","#AAAA11","#6633CC","#E67300","#329262","#5574A6"],"servers":[{"server_name":"Survival","last_seen":"Today, 01:48","registered":"Tuesday, 15:40","gm_series":[{"data":[["SURVIVAL",1571],["SPECTATOR",0],["CREATIVE",0],["ADVENTURE",0]],"name":"NordicEraI","id":"NordicEraI"},{"data":[["SURVIVAL",9540096],["SPECTATOR",0],["CREATIVE",0],["ADVENTURE",0]],"name":"NordicII","id":"NordicII"}],"playtime":"2h 39m 1s","session_median":"11m 24s","world_pie_series":[{"name":"NordicEraI","y":1571,"color":"#0099C6","drilldown":"NordicEraI"},{"name":"NordicII","y":9540096,"color":"#66AA00","drilldown":"NordicII"}],"operator":false,"mob_kills":6,"afk_time":"9m 21s","session_count":5,"player_kills":0,"longest_session_length":"1h 45m 48s","banned":false,"deaths":14}],"server_pie_series":[{"name":"Survival","y":9541667}],"online_activity":{"session_count_30d":5,"session_count_7d":5,"afk_time_7d":"9m 21s","mob_kill_count_30d":6,"active_playtime_7d":"2h 29m 39s","mob_kill_count_7d":6,"afk_time_30d":"9m 21s","average_session_length_30d":"31m 48s","death_count_30d":14,"active_playtime_30d":"2h 29m 39s","average_session_length_7d":"31m 48s","median_session_length_7d":"11m 24s","median_session_length_30d":"11m 24s","playtime_30d":"2h 39m 1s","player_kill_count_30d":0,"death_count_7d":14,"playtime_7d":"2h 39m 1s","player_kill_count_7d":0},"player_kills":[],"sessions_per_page":50,"punchcard_series":[{"x":0,"y":0,"z":0,"marker":{"radius":0}},{"x":3600000,"y":0,"z":0,"marker":{"radius":0}},{"x":7200000,"y":0,"z":0,"marker":{"radius":0}},{"x":10800000,"y":0,"z":0,"marker":{"radius":0}},{"x":14400000,"y":0,"z":0,"marker":{"radius":0}},{"x":18000000,"y":0,"z":0,"marker":{"radius":0}},{"x":21600000,"y":0,"z":0,"marker":{"radius":0}},{"x":25200000,"y":0,"z":0,"marker":{"radius":0}},{"x":28800000,"y":0,"z":0,"marker":{"radius":0}},{"x":32400000,"y":0,"z":0,"marker":{"radius":0}},{"x":36000000,"y":0,"z":0,"marker":{"radius":0}},{"x":39600000,"y":0,"z":0,"marker":{"radius":0}},{"x":43200000,"y":0,"z":0,"marker":{"radius":0}},{"x":46800000,"y":0,"z":0,"marker":{"radius":0}},{"x":50400000,"y":0,"z":0,"marker":{"radius":0}},{"x":54000000,"y":0,"z":0,"marker":{"radius":0}},{"x":57600000,"y":0,"z":0,"marker":{"radius":0}},{"x":61200000,"y":0,"z":0,"marker":{"radius":0}},{"x":64800000,"y":0,"z":0,"marker":{"radius":0}},{"x":68400000,"y":0,"z":0,"marker":{"radius":0}},{"x":72000000,"y":0,"z":0,"marker":{"radius":0}},{"x":75600000,"y":0,"z":0,"marker":{"radius":0}},{"x":79200000,"y":0,"z":0,"marker":{"radius":0}},{"x":82800000,"y":0,"z":0,"marker":{"radius":0}},{"x":0,"y":1,"z":0,"marker":{"radius":0}},{"x":3600000,"y":1,"z":0,"marker":{"radius":0}},{"x":7200000,"y":1,"z":0,"marker":{"radius":0}},{"x":10800000,"y":1,"z":0,"marker":{"radius":0}},{"x":14400000,"y":1,"z":0,"marker":{"radius":0}},{"x":18000000,"y":1,"z":0,"marker":{"radius":0}},{"x":21600000,"y":1,"z":0,"marker":{"radius":0}},{"x":25200000,"y":1,"z":0,"marker":{"radius":0}},{"x":28800000,"y":1,"z":0,"marker":{"radius":0}},{"x":32400000,"y":1,"z":0,"marker":{"radius":0}},{"x":36000000,"y":1,"z":0,"marker":{"radius":0}},{"x":39600000,"y":1,"z":0,"marker":{"radius":0}},{"x":43200000,"y":1,"z":0,"marker":{"radius":0}},{"x":46800000,"y":1,"z":0,"marker":{"radius":0}},{"x":50400000,"y":1,"z":0,"marker":{"radius":0}},{"x":54000000,"y":1,"z":9,"marker":{"radius":9}},{"x":57600000,"y":1,"z":9,"marker":{"radius":9}},{"x":61200000,"y":1,"z":0,"marker":{"radius":0}},{"x":64800000,"y":1,"z":14,"marker":{"radius":14}},{"x":68400000,"y":1,"z":0,"marker":{"radius":0}},{"x":72000000,"y":1,"z":0,"marker":{"radius":0}},{"x":75600000,"y":1,"z":0,"marker":{"radius":0}},{"x":79200000,"y":1,"z":0,"marker":{"radius":0}},{"x":82800000,"y":1,"z":0,"marker":{"radius":0}},{"x":0,"y":2,"z":0,"marker":{"radius":0}},{"x":3600000,"y":2,"z":0,"marker":{"radius":0}},{"x":7200000,"y":2,"z":0,"marker":{"radius":0}},{"x":10800000,"y":2,"z":0,"marker":{"radius":0}},{"x":14400000,"y":2,"z":0,"marker":{"radius":0}},{"x":18000000,"y":2,"z":0,"marker":{"radius":0}},{"x":21600000,"y":2,"z":0,"marker":{"radius":0}},{"x":25200000,"y":2,"z":0,"marker":{"radius":0}},{"x":28800000,"y":2,"z":0,"marker":{"radius":0}},{"x":32400000,"y":2,"z":0,"marker":{"radius":0}},{"x":36000000,"y":2,"z":0,"marker":{"radius":0}},{"x":39600000,"y":2,"z":0,"marker":{"radius":0}},{"x":43200000,"y":2,"z":0,"marker":{"radius":0}},{"x":46800000,"y":2,"z":0,"marker":{"radius":0}},{"x":50400000,"y":2,"z":0,"marker":{"radius":0}},{"x":54000000,"y":2,"z":0,"marker":{"radius":0}},{"x":57600000,"y":2,"z":0,"marker":{"radius":0}},{"x":61200000,"y":2,"z":0,"marker":{"radius":0}},{"x":64800000,"y":2,"z":0,"marker":{"radius":0}},{"x":68400000,"y":2,"z":0,"marker":{"radius":0}},{"x":72000000,"y":2,"z":0,"marker":{"radius":0}},{"x":75600000,"y":2,"z":0,"marker":{"radius":0}},{"x":79200000,"y":2,"z":0,"marker":{"radius":0}},{"x":82800000,"y":2,"z":0,"marker":{"radius":0}},{"x":0,"y":3,"z":0,"marker":{"radius":0}},{"x":3600000,"y":3,"z":0,"marker":{"radius":0}},{"x":7200000,"y":3,"z":0,"marker":{"radius":0}},{"x":10800000,"y":3,"z":0,"marker":{"radius":0}},{"x":14400000,"y":3,"z":0,"marker":{"radius":0}},{"x":18000000,"y":3,"z":0,"marker":{"radius":0}},{"x":21600000,"y":3,"z":0,"marker":{"radius":0}},{"x":25200000,"y":3,"z":0,"marker":{"radius":0}},{"x":28800000,"y":3,"z":0,"marker":{"radius":0}},{"x":32400000,"y":3,"z":0,"marker":{"radius":0}},{"x":36000000,"y":3,"z":0,"marker":{"radius":0}},{"x":39600000,"y":3,"z":0,"marker":{"radius":0}},{"x":43200000,"y":3,"z":0,"marker":{"radius":0}},{"x":46800000,"y":3,"z":0,"marker":{"radius":0}},{"x":50400000,"y":3,"z":0,"marker":{"radius":0}},{"x":54000000,"y":3,"z":0,"marker":{"radius":0}},{"x":57600000,"y":3,"z":0,"marker":{"radius":0}},{"x":61200000,"y":3,"z":0,"marker":{"radius":0}},{"x":64800000,"y":3,"z":0,"marker":{"radius":0}},{"x":68400000,"y":3,"z":0,"marker":{"radius":0}},{"x":72000000,"y":3,"z":0,"marker":{"radius":0}},{"x":75600000,"y":3,"z":0,"marker":{"radius":0}},{"x":79200000,"y":3,"z":0,"marker":{"radius":0}},{"x":82800000,"y":3,"z":0,"marker":{"radius":0}},{"x":0,"y":4,"z":0,"marker":{"radius":0}},{"x":3600000,"y":4,"z":0,"marker":{"radius":0}},{"x":7200000,"y":4,"z":0,"marker":{"radius":0}},{"x":10800000,"y":4,"z":0,"marker":{"radius":0}},{"x":14400000,"y":4,"z":0,"marker":{"radius":0}},{"x":18000000,"y":4,"z":0,"marker":{"radius":0}},{"x":21600000,"y":4,"z":0,"marker":{"radius":0}},{"x":25200000,"y":4,"z":0,"marker":{"radius":0}},{"x":28800000,"y":4,"z":0,"marker":{"radius":0}},{"x":32400000,"y":4,"z":0,"marker":{"radius":0}},{"x":36000000,"y":4,"z":0,"marker":{"radius":0}},{"x":39600000,"y":4,"z":0,"marker":{"radius":0}},{"x":43200000,"y":4,"z":0,"marker":{"radius":0}},{"x":46800000,"y":4,"z":0,"marker":{"radius":0}},{"x":50400000,"y":4,"z":0,"marker":{"radius":0}},{"x":54000000,"y":4,"z":0,"marker":{"radius":0}},{"x":57600000,"y":4,"z":0,"marker":{"radius":0}},{"x":61200000,"y":4,"z":0,"marker":{"radius":0}},{"x":64800000,"y":4,"z":0,"marker":{"radius":0}},{"x":68400000,"y":4,"z":0,"marker":{"radius":0}},{"x":72000000,"y":4,"z":0,"marker":{"radius":0}},{"x":75600000,"y":4,"z":0,"marker":{"radius":0}},{"x":79200000,"y":4,"z":0,"marker":{"radius":0}},{"x":82800000,"y":4,"z":0,"marker":{"radius":0}},{"x":0,"y":5,"z":0,"marker":{"radius":0}},{"x":3600000,"y":5,"z":9,"marker":{"radius":9}},{"x":7200000,"y":5,"z":0,"marker":{"radius":0}},{"x":10800000,"y":5,"z":0,"marker":{"radius":0}},{"x":14400000,"y":5,"z":0,"marker":{"radius":0}},{"x":18000000,"y":5,"z":0,"marker":{"radius":0}},{"x":21600000,"y":5,"z":0,"marker":{"radius":0}},{"x":25200000,"y":5,"z":0,"marker":{"radius":0}},{"x":28800000,"y":5,"z":0,"marker":{"radius":0}},{"x":32400000,"y":5,"z":0,"marker":{"radius":0}},{"x":36000000,"y":5,"z":0,"marker":{"radius":0}},{"x":39600000,"y":5,"z":0,"marker":{"radius":0}},{"x":43200000,"y":5,"z":0,"marker":{"radius":0}},{"x":46800000,"y":5,"z":0,"marker":{"radius":0}},{"x":50400000,"y":5,"z":0,"marker":{"radius":0}},{"x":54000000,"y":5,"z":0,"marker":{"radius":0}},{"x":57600000,"y":5,"z":0,"marker":{"radius":0}},{"x":61200000,"y":5,"z":0,"marker":{"radius":0}},{"x":64800000,"y":5,"z":0,"marker":{"radius":0}},{"x":68400000,"y":5,"z":0,"marker":{"radius":0}},{"x":72000000,"y":5,"z":0,"marker":{"radius":0}},{"x":75600000,"y":5,"z":0,"marker":{"radius":0}},{"x":79200000,"y":5,"z":0,"marker":{"radius":0}},{"x":82800000,"y":5,"z":0,"marker":{"radius":0}},{"x":0,"y":6,"z":0,"marker":{"radius":0}},{"x":3600000,"y":6,"z":0,"marker":{"radius":0}},{"x":7200000,"y":6,"z":0,"marker":{"radius":0}},{"x":10800000,"y":6,"z":0,"marker":{"radius":0}},{"x":14400000,"y":6,"z":0,"marker":{"radius":0}},{"x":18000000,"y":6,"z":0,"marker":{"radius":0}},{"x":21600000,"y":6,"z":0,"marker":{"radius":0}},{"x":25200000,"y":6,"z":0,"marker":{"radius":0}},{"x":28800000,"y":6,"z":0,"marker":{"radius":0}},{"x":32400000,"y":6,"z":0,"marker":{"radius":0}},{"x":36000000,"y":6,"z":0,"marker":{"radius":0}},{"x":39600000,"y":6,"z":0,"marker":{"radius":0}},{"x":43200000,"y":6,"z":0,"marker":{"radius":0}},{"x":46800000,"y":6,"z":0,"marker":{"radius":0}},{"x":50400000,"y":6,"z":0,"marker":{"radius":0}},{"x":54000000,"y":6,"z":0,"marker":{"radius":0}},{"x":57600000,"y":6,"z":0,"marker":{"radius":0}},{"x":61200000,"y":6,"z":0,"marker":{"radius":0}},{"x":64800000,"y":6,"z":0,"marker":{"radius":0}},{"x":68400000,"y":6,"z":0,"marker":{"radius":0}},{"x":72000000,"y":6,"z":0,"marker":{"radius":0}},{"x":75600000,"y":6,"z":0,"marker":{"radius":0}},{"x":79200000,"y":6,"z":0,"marker":{"radius":0}},{"x":82800000,"y":6,"z":0,"marker":{"radius":0}}],"nicknames":[{"nickname":"toitstar","server":"Survival","date":"Today, 01:48"}],"connections":[{"geolocation":"Finland","date":"Today, 01:37"}],"info":{"kick_count":0,"last_seen":"Today, 01:48","favorite_server":"Survival","mob_kill_count":6,"player_kill_count":0,"registered":"Tuesday, 15:40","activity_index_group":"Irregular","playtime":"2h 39m 1s","session_median":"11m 24s","active_playtime":"2h 29m 39s","operator":false,"afk_time":"9m 21s","death_count":14,"worst_ping":"2584 ms","session_count":5,"online":false,"longest_session_length":"1h 45m 48s","best_ping":"16 ms","banned":false,"activity_index":"1.48","average_ping":"159.92 ms"},"first_day":1}